Entrega_Final/raiz/control.v
module control (clk, rst, init, Zero, Neg, load, shift, load_Temp, setRoot, Dec, update_RAC, done);
    input clk;
    input rst;
    input init;
    input Neg;
    input Zero;
    output reg load;
    output reg shift;
    output reg load_Temp;
    output reg Dec;
    output reg setRoot;
    output reg update_RAC;
    output reg done;

    //estados
    parameter Start = 3'b000;
    parameter Check_Counter = 3'b001;
    parameter Shift = 3'b010;
    parameter LoadTemp = 3'b011;
    parameter Check_RAC = 3'b100;
    parameter Update_Root = 3'b101;
    parameter Dec_Counter = 3'b110;
    parameter Done = 3'b111;

    //registro de estado
    reg [2:0] STATE;
    reg [4:0] Count;

always @(posedge clk or posedge rst) 
begin
    if (rst) 
    begin
        STATE <= Start;    
    end
    else
        begin
            case (STATE)
                Start:
                begin
                    Count<=0;
                    if (init) 
                    begin
                        STATE <= Check_Counter;
                    end
                    else 
                        STATE <= Start;
                end
                Check_Counter:
                begin
                    if (Zero) 
                    begin
                        STATE <= Done;
                    end
                    else
                        STATE <= Shift;
                end
                Shift:
                begin
                    STATE <= LoadTemp;
                end
                LoadTemp:
                begin
                    STATE <= Check_RAC;
                end
                Check_RAC:
                begin
                    if (Neg) 
                    begin
                        STATE <= Dec_Counter;    
                    end
                    else
                        STATE <= Update_Root;
                end
                Update_Root:
                begin
                    STATE <= Dec_Counter;
                end
                Dec_Counter:
                begin
                    STATE <= Check_Counter;
                end
                Done:
                begin
                    Count <= Count+1;
                    if (Count >=28) 
                    begin
                        STATE <= Start;
                    end
                    else
                        STATE <= Done;
                end

                default: STATE <= Start;
            endcase
        end
end
// activar salidas
always @(*) 
begin
    case (STATE)
        Start:
        begin
            Dec = 0;
            load = 1;
            shift = 0;
            setRoot = 0;
            load_Temp = 0;
            update_RAC = 0;
            done = 0;
        end
        Check_Counter:
        begin
            Dec = 0;
            load = 0;
            shift = 0;
            setRoot = 0;
            load_Temp = 0;
            update_RAC = 0;
            done = 0;
        end
        Shift:
        begin
            Dec = 0;
            load = 0;
            shift = 1;
            setRoot = 0;
            load_Temp = 0;
            update_RAC = 0;
            done = 0;
        end
        LoadTemp:
        begin
            Dec = 0;
            load = 0;
            shift = 0;
            setRoot = 0;
            load_Temp = 1;
            update_RAC = 0;
            done = 0;
        end
        Check_RAC:
        begin
            Dec = 0;
            load = 0;
            shift = 0;
            setRoot = 0;
            load_Temp = 0;
            update_RAC = 0;
            done = 0;
        end
        Update_Root:
        begin
            Dec = 0;
            load = 0;
            shift = 0;
            setRoot = 1;
            load_Temp = 0;
            update_RAC = 1;
            done = 0;
        end
        Dec_Counter:
        begin
            Dec = 1;
            load = 0;
            shift = 0;
            setRoot = 0;
            load_Temp = 0;
            update_RAC = 0;
            done = 0;
        end
        Done:
        begin
            Dec = 0;
            load = 0;
            shift = 0;
            setRoot = 0;
            load_Temp = 0;
            update_RAC = 0;
            done = 1;
        end
        default:
        begin
            Dec = 0;
            load = 0;
            shift = 0;
            setRoot = 0;
            load_Temp = 0;
            update_RAC = 0;
            done = 0;
        end
    endcase    
end

endmodule

Entrega_Final/raiz/counter.v
module counter (clk, load, Dec, out_c);
    //señales de control
    input clk;
    input load;
    input Dec;
    output reg [3:0]out_c;
    always @(posedge clk) 
    begin
        if (load) 
        begin
            out_c <= 4'd8;
        end
        else if (Dec) 
        begin
            out_c <= out_c - 1'b1;
        end
    end
    
endmodule

Entrega_Final/raiz/comp.v
module comp (out_c, Zero);
    //entrada del comparador
    input [3:0]out_c;
    // salida del comparador
    output Zero;
    // comparación
    assign Zero = (out_c == 0);   
endmodule

Entrega_Final/raiz/Subtractor.v
module Subtractor (RAC, Temp, SUM, Neg);
    // entradas
    input [15:0] RAC;
    input [7:0] Temp;
    // salidas
    output reg [16:0] SUM;
    output Neg;

    assign Neg = SUM[16];

    always @(*) 
    begin
       SUM = RAC - { 8'b0, Temp[6:0], 1'b1};
    end

endmodule

Entrega_Final/raiz/regTemp.v
module regTemp (clk, load, load_Temp, Temp, Root);
    //señales de control
    input clk;
    input load;
    input load_Temp;
    // entrada de datos
    input [7:0] Root;
    // salida del modulo
    output reg [7:0] Temp;
    always @(posedge clk) 
    begin
        if (load) 
        begin
            Temp <= 8'd0;    
        end    
        else if (load_Temp) 
        begin
            Temp <= Root;    
        end
    end
endmodule

Entrega_Final/raiz/regRoot.v
module regRoot (clk, load, shift, setRoot, Root);
    //señales de control 
    input clk;
    input load;
    input shift;
    input setRoot;
    // salida
    output reg [7:0] Root;
    always @(posedge clk) 
    begin
        if (load) 
        begin
            Root <= 8'd0;    
        end
        else if (shift) 
        begin
            Root <= Root << 1;    
        end
        else if (setRoot) 
        begin
            Root[0] <= 1'b1;     
        end
    end
endmodule

Entrega_Final/raiz/regRACRad.v
module regRACRad (clk, load, shift, update_RAC, in_Rad, SUM, RAC, Rad);
    //señales de control
    input clk;
    input load;
    input shift;
    input update_RAC;
    // datos del modulo
    input [15:0] in_Rad;
    input [16:0] SUM;
    // salidas
    output reg [15:0] RAC;
    output reg [15:0] Rad;

    always @(posedge clk) 
    begin
        if (load) 
        begin
            RAC <= 16'd0;
            Rad <= in_Rad;
        end
        else if (shift) 
        begin
            {RAC,Rad} <= {RAC,Rad} << 2;    
        end
        else if (update_RAC) 
        begin
            RAC <= SUM[15:0];
        end    
    end
endmodule

Entrega_Final/raiz/raiz.v
module raiz (clk, rst, init, Rad, Root, done);
    // entradas
    input clk;
    input rst;
    input init;
    input [15:0] Rad;
    //salidas
    output [7:0] Root;
    output done;
    //señales de control
    wire load;
    wire shift;
    wire load_Temp;
    wire setRoot;
    wire Dec;
    wire update_RAC;

    wire [15:0] w_RAC;
    wire [15:0] w_Rad;
    wire [7:0] w_Root;
    wire [7:0] w_Temp;
    wire [16:0] SUM;
    wire [3:0] out_c;
    wire Neg;
    wire Zero;

regRACRad Racrad0(.clk(clk), .load(load), .shift(shift), .update_RAC(update_RAC), .in_Rad(Rad), .SUM(SUM), .RAC(w_RAC), .Rad(w_Rad));
regRoot Root0(.clk(clk), .load(load), .shift(shift), .setRoot(setRoot), .Root(w_Root));
regTemp temp0(.clk(clk), .load(load), .load_Temp(load_Temp), .Temp(w_Temp), .Root(w_Root));
Subtractor sub0(.RAC(w_RAC), .Temp(w_Temp), .SUM(SUM), .Neg(Neg));
comp comp0(.out_c(out_c), .Zero(Zero));
counter cont0(.clk(clk), .load(load), .Dec(Dec), .out_c(out_c));
control ctrl0(.clk(clk), .rst(rst), .init(init), .Zero(Zero), .Neg(Neg), .load(load), .shift(shift), .load_Temp(load_Temp), .setRoot(setRoot), .Dec(Dec), .update_RAC(update_RAC), .done(done));
assign Root = w_Root;

endmodule

Entrega_Final/raiz/raiz_TB.v
module raiz_TB;
    reg clk;
    reg rst;
    reg init;
    reg [15:0] Rad;
    wire [7:0] Root;
    wire done;

raiz uut(.clk(clk), .rst(rst), .init(init), .Rad(Rad), .Root(Root), .done(done));
initial begin
    clk=0;
    forever #20 clk=~clk;
end
initial begin
    $dumpfile("raiz_TB.vcd");
    $dumpvars(0, raiz_TB);

    rst=1;
    init=0;
    Rad=16'd32;
    @(posedge clk);
    rst=0;
    @(posedge clk);
    init=1;
    @(posedge clk);
    init=0;
    wait(done);
    #40;
    Rad=16'd16;
    @(posedge clk);
    rst=1;
    @(posedge clk);
    rst=0;
    @(posedge clk);
    init=1;
    @(posedge clk);
    init=0;
    wait(done);
    #40;
    Rad=16'd65535;
    @(posedge clk);
    rst=1;
    @(posedge clk);
    rst=0;
    @(posedge clk);
    init=1;
    @(posedge clk);
    init=0;
    wait(done);
    #40;
    Rad=16'd1;
    @(posedge clk);
    rst=1;
    @(posedge clk);
    rst=0;
    @(posedge clk);
    init=1;
    @(posedge clk);
    init=0;
    wait(done);
    #40;

    $finish;
end
    
endmodule

Entrega_Final/raiz/raiz_TB.vcd
$date
	Thu Jul 16 11:00:32 2026
$end
$version
	Icarus Verilog
$end
$timescale
	1s
$end
$scope module raiz_TB $end
$var wire 1 ! done $end
$var wire 8 " Root [7:0] $end
$var reg 16 # Rad [15:0] $end
$var reg 1 $ clk $end
$var reg 1 % init $end
$var reg 1 & rst $end
$scope module uut $end
$var wire 16 ' Rad [15:0] $end
$var wire 8 ( Root [7:0] $end
$var wire 1 $ clk $end
$var wire 1 % init $end
$var wire 1 & rst $end
$var wire 8 ) w_Temp [7:0] $end
$var wire 8 * w_Root [7:0] $end
$var wire 16 + w_Rad [15:0] $end
$var wire 16 , w_RAC [15:0] $end
$var wire 1 - update_RAC $end
$var wire 1 . shift $end
$var wire 1 / setRoot $end
$var wire 4 0 out_c [3:0] $end
$var wire 1 1 load_Temp $end
$var wire 1 2 load $end
$var wire 1 ! done $end
$var wire 1 3 Zero $end
$var wire 17 4 SUM [16:0] $end
$var wire 1 5 Neg $end
$var wire 1 6 Dec $end
$scope module Racrad0 $end
$var wire 1 $ clk $end
$var wire 16 7 in_Rad [15:0] $end
$var wire 1 - update_RAC $end
$var wire 1 . shift $end
$var wire 1 2 load $end
$var wire 17 8 SUM [16:0] $end
$var reg 16 9 RAC [15:0] $end
$var reg 16 : Rad [15:0] $end
$upscope $end
$scope module Root0 $end
$var wire 1 $ clk $end
$var wire 1 . shift $end
$var wire 1 / setRoot $end
$var wire 1 2 load $end
$var reg 8 ; Root [7:0] $end
$upscope $end
$scope module comp0 $end
$var wire 4 < out_c [3:0] $end
$var wire 1 3 Zero $end
$upscope $end
$scope module cont0 $end
$var wire 1 $ clk $end
$var wire 1 2 load $end
$var wire 1 6 Dec $end
$var reg 4 = out_c [3:0] $end
$upscope $end
$scope module ctrl0 $end
$var wire 1 3 Zero $end
$var wire 1 $ clk $end
$var wire 1 % init $end
$var wire 1 & rst $end
$var wire 1 5 Neg $end
$var parameter 3 > Check_Counter $end
$var parameter 3 ? Check_RAC $end
$var parameter 3 @ Dec_Counter $end
$var parameter 3 A Done $end
$var parameter 3 B LoadTemp $end
$var parameter 3 C Shift $end
$var parameter 3 D Start $end
$var parameter 3 E Update_Root $end
$var reg 5 F Count [4:0] $end
$var reg 1 6 Dec $end
$var reg 3 G STATE [2:0] $end
$var reg 1 ! done $end
$var reg 1 2 load $end
$var reg 1 1 load_Temp $end
$var reg 1 / setRoot $end
$var reg 1 . shift $end
$var reg 1 - update_RAC $end
$upscope $end
$scope module sub0 $end
$var wire 16 H RAC [15:0] $end
$var wire 8 I Temp [7:0] $end
$var wire 1 5 Neg $end
$var reg 17 J SUM [16:0] $end
$upscope $end
$scope module temp0 $end
$var wire 8 K Root [7:0] $end
$var wire 1 $ clk $end
$var wire 1 2 load $end
$var wire 1 1 load_Temp $end
$var reg 8 L Temp [7:0] $end
$upscope $end
$upscope $end
$upscope $end
$enddefinitions $end
$comment Show the parameter values. $end
$dumpall
b101 E
b0 D
b10 C
b11 B
b111 A
b110 @
b100 ?
b1 >
$end
#0
$dumpvars
bx L
bx K
bx J
bx I
bx H
b0 G
bx F
bx =
bx <
bx ;
bx :
bx 9
bx 8
b100000 7
06
x5
bx 4
x3
12
01
bx 0
0/
0.
0-
bx ,
bx +
bx *
bx )
bx (
b100000 '
1&
0%
0$
b100000 #
bx "
0!
$end
#20
15
b11111111111111111 4
b11111111111111111 8
b11111111111111111 J
b100000 +
b100000 :
b0 ,
b0 9
b0 H
b0 "
b0 (
b0 *
b0 ;
b0 K
b0 )
b0 I
b0 L
03
b1000 0
b1000 <
b1000 =
0&
1$
#40
0$
#60
b0 F
1%
1$
#80
0$
#100
02
b1 G
0%
1$
#120
0$
#140
1.
b10 G
1$
#160
0$
#180
11
0.
b10000000 +
b10000000 :
b11 G
1$
#200
0$
#220
01
b100 G
1$
#240
0$
#260
16
b110 G
1$
#280
0$
#300
06
b111 0
b111 <
b111 =
b1 G
1$
#320
0$
#340
1.
b10 G
1$
#360
0$
#380
11
0.
b1000000000 +
b1000000000 :
b11 G
1$
#400
0$
#420
01
b100 G
1$
#440
0$
#460
16
b110 G
1$
#480
0$
#500
06
b110 0
b110 <
b110 =
b1 G
1$
#520
0$
#540
1.
b10 G
1$
#560
0$
#580
11
0.
b100000000000 +
b100000000000 :
b11 G
1$
#600
0$
#620
01
b100 G
1$
#640
0$
#660
16
b110 G
1$
#680
0$
#700
06
b101 0
b101 <
b101 =
b1 G
1$
#720
0$
#740
1.
b10 G
1$
#760
0$
#780
11
0.
b10000000000000 +
b10000000000000 :
b11 G
1$
#800
0$
#820
01
b100 G
1$
#840
0$
#860
16
b110 G
1$
#880
0$
#900
06
b100 0
b100 <
b100 =
b1 G
1$
#920
0$
#940
1.
b10 G
1$
#960
0$
#980
11
0.
b1000000000000000 +
b1000000000000000 :
b11 G
1$
#1000
0$
#1020
01
b100 G
1$
#1040
0$
#1060
16
b110 G
1$
#1080
0$
#1100
06
b11 0
b11 <
b11 =
b1 G
1$
#1120
0$
#1140
1.
b10 G
1$
#1160
0$
#1180
05
b1 4
b1 8
b1 J
11
0.
b10 ,
b10 9
b10 H
b0 +
b0 :
b11 G
1$
#1200
0$
#1220
01
b100 G
1$
#1240
0$
#1260
1-
1/
b101 G
1$
#1280
0$
#1300
b0 4
b0 8
b0 J
0-
0/
16
b1 ,
b1 9
b1 H
b1 "
b1 (
b1 *
b1 ;
b1 K
b110 G
1$
#1320
0$
#1340
06
b10 0
b10 <
b10 =
b1 G
1$
#1360
0$
#1380
1.
b10 G
1$
#1400
0$
#1420
b11 4
b11 8
b11 J
11
0.
b10 "
b10 (
b10 *
b10 ;
b10 K
b100 ,
b100 9
b100 H
b11 G
1$
#1440
0$
#1460
15
b11111111111111111 4
b11111111111111111 8
b11111111111111111 J
01
b10 )
b10 I
b10 L
b100 G
1$
#1480
0$
#1500
16
b110 G
1$
#1520
0$
#1540
06
b1 0
b1 <
b1 =
b1 G
1$
#1560
0$
#1580
1.
b10 G
1$
#1600
0$
#1620
05
b1011 4
b1011 8
b1011 J
11
0.
b10000 ,
b10000 9
b10000 H
b100 "
b100 (
b100 *
b100 ;
b100 K
b11 G
1$
#1640
0$
#1660
b111 4
b111 8
b111 J
01
b100 )
b100 I
b100 L
b100 G
1$
#1680
0$
#1700
1-
1/
b101 G
1$
#1720
0$
#1740
15
b11111111111111110 4
b11111111111111110 8
b11111111111111110 J
0-
0/
16
b101 "
b101 (
b101 *
b101 ;
b101 K
b111 ,
b111 9
b111 H
b110 G
1$
#1760
0$
#1780
06
13
b0 0
b0 <
b0 =
b1 G
1$
#1800
0$
#1820
1!
b111 G
1$
#1840
0$
#1860
0!
12
b0 G
b1 F
1&
1$
b10000 #
b10000 '
b10000 7
#1880
0$
#1900
b11111111111111111 4
b11111111111111111 8
b11111111111111111 J
03
b1000 0
b1000 <
b1000 =
b0 )
b0 I
b0 L
b0 "
b0 (
b0 *
b0 ;
b0 K
b10000 +
b10000 :
b0 ,
b0 9
b0 H
0&
1$
#1920
0$
#1940
b0 F
1%
1$
#1960
0$
#1980
02
b1 G
0%
1$
#2000
0$
#2020
1.
b10 G
1$
#2040
0$
#2060
11
0.
b1000000 +
b1000000 :
b11 G
1$
#2080
0$
#2100
01
b100 G
1$
#2120
0$
#2140
16
b110 G
1$
#2160
0$
#2180
06
b111 0
b111 <
b111 =
b1 G
1$
#2200
0$
#2220
1.
b10 G
1$
#2240
0$
#2260
11
0.
b100000000 +
b100000000 :
b11 G
1$
#2280
0$
#2300
01
b100 G
1$
#2320
0$
#2340
16
b110 G
1$
#2360
0$
#2380
06
b110 0
b110 <
b110 =
b1 G
1$
#2400
0$
#2420
1.
b10 G
1$
#2440
0$
#2460
11
0.
b10000000000 +
b10000000000 :
b11 G
1$
#2480
0$
#2500
01
b100 G
1$
#2520
0$
#2540
16
b110 G
1$
#2560
0$
#2580
06
b101 0
b101 <
b101 =
b1 G
1$
#2600
0$
#2620
1.
b10 G
1$
#2640
0$
#2660
11
0.
b1000000000000 +
b1000000000000 :
b11 G
1$
#2680
0$
#2700
01
b100 G
1$
#2720
0$
#2740
16
b110 G
1$
#2760
0$
#2780
06
b100 0
b100 <
b100 =
b1 G
1$
#2800
0$
#2820
1.
b10 G
1$
#2840
0$
#2860
11
0.
b100000000000000 +
b100000000000000 :
b11 G
1$
#2880
0$
#2900
01
b100 G
1$
#2920
0$
#2940
16
b110 G
1$
#2960
0$
#2980
06
b11 0
b11 <
b11 =
b1 G
1$
#3000
0$
#3020
1.
b10 G
1$
#3040
0$
#3060
05
b0 4
b0 8
b0 J
11
0.
b1 ,
b1 9
b1 H
b0 +
b0 :
b11 G
1$
#3080
0$
#3100
01
b100 G
1$
#3120
0$
#3140
1-
1/
b101 G
1$
#3160
0$
#3180
15
b11111111111111111 4
b11111111111111111 8
b11111111111111111 J
0-
0/
16
b1 "
b1 (
b1 *
b1 ;
b1 K
b0 ,
b0 9
b0 H
b110 G
1$
#3200
0$
#3220
06
b10 0
b10 <
b10 =
b1 G
1$
#3240
0$
#3260
1.
b10 G
1$
#3280
0$
#3300
11
0.
b10 "
b10 (
b10 *
b10 ;
b10 K
b11 G
1$
#3320
0$
#3340
b11111111111111011 4
b11111111111111011 8
b11111111111111011 J
01
b10 )
b10 I
b10 L
b100 G
1$
#3360
0$
#3380
16
b110 G
1$
#3400
0$
#3420
06
b1 0
b1 <
b1 =
b1 G
1$
#3440
0$
#3460
1.
b10 G
1$
#3480
0$
#3500
11
0.
b100 "
b100 (
b100 *
b100 ;
b100 K
b11 G
1$
#3520
0$
#3540
b11111111111110111 4
b11111111111110111 8
b11111111111110111 J
01
b100 )
b100 I
b100 L
b100 G
1$
#3560
0$
#3580
16
b110 G
1$
#3600
0$
#3620
06
13
b0 0
b0 <
b0 =
b1 G
1$
#3640
0$
#3660
1!
b111 G
1$
#3680
0$
#3700
0!
12
b0 G
b1 F
1&
1$
b1111111111111111 #
b1111111111111111 '
b1111111111111111 7
#3720
0$
#3740
b11111111111111111 4
b11111111111111111 8
b11111111111111111 J
03
b1000 0
b1000 <
b1000 =
b0 )
b0 I
b0 L
b0 "
b0 (
b0 *
b0 ;
b0 K
b1111111111111111 +
b1111111111111111 :
0&
1$
#3760
0$
#3780
b0 F
1%
1$
#3800
0$
#3820
02
b1 G
0%
1$
#3840
0$
#3860
1.
b10 G
1$
#3880
0$
#3900
05
b10 4
b10 8
b10 J
11
0.
b11 ,
b11 9
b11 H
b1111111111111100 +
b1111111111111100 :
b11 G
1$
#3920
0$
#3940
01
b100 G
1$
#3960
0$
#3980
1-
1/
b101 G
1$
#4000
0$
#4020
b1 4
b1 8
b1 J
0-
0/
16
b10 ,
b10 9
b10 H
b1 "
b1 (
b1 *
b1 ;
b1 K
b110 G
1$
#4040
0$
#4060
06
b111 0
b111 <
b111 =
b1 G
1$
#4080
0$
#4100
1.
b10 G
1$
#4120
0$
#4140
b1010 4
b1010 8
b1010 J
11
0.
b10 "
b10 (
b10 *
b10 ;
b10 K
b1011 ,
b1011 9
b1011 H
b1111111111110000 +
b1111111111110000 :
b11 G
1$
#4160
0$
#4180
b110 4
b110 8
b110 J
01
b10 )
b10 I
b10 L
b100 G
1$
#4200
0$
#4220
1-
1/
b101 G
1$
#4240
0$
#4260
b1 4
b1 8
b1 J
0-
0/
16
b110 ,
b110 9
b110 H
b11 "
b11 (
b11 *
b11 ;
b11 K
b110 G
1$
#4280
0$
#4300
06
b110 0
b110 <
b110 =
b1 G
1$
#4320
0$
#4340
1.
b10 G
1$
#4360
0$
#4380
b10110 4
b10110 8
b10110 J
11
0.
b110 "
b110 (
b110 *
b110 ;
b110 K
b11011 ,
b11011 9
b11011 H
b1111111111000000 +
b1111111111000000 :
b11 G
1$
#4400
0$
#4420
b1110 4
b1110 8
b1110 J
01
b110 )
b110 I
b110 L
b100 G
1$
#4440
0$
#4460
1-
1/
b101 G
1$
#4480
0$
#4500
b1 4
b1 8
b1 J
0-
0/
16
b1110 ,
b1110 9
b1110 H
b111 "
b111 (
b111 *
b111 ;
b111 K
b110 G
1$
#4520
0$
#4540
06
b101 0
b101 <
b101 =
b1 G
1$
#4560
0$
#4580
1.
b10 G
1$
#4600
0$
#4620
b101110 4
b101110 8
b101110 J
11
0.
b1110 "
b1110 (
b1110 *
b1110 ;
b1110 K
b111011 ,
b111011 9
b111011 H
b1111111100000000 +
b1111111100000000 :
b11 G
1$
#4640
0$
#4660
b11110 4
b11110 8
b11110 J
01
b1110 )
b1110 I
b1110 L
b100 G
1$
#4680
0$
#4700
1-
1/
b101 G
1$
#4720
0$
#4740
b1 4
b1 8
b1 J
0-
0/
16
b11110 ,
b11110 9
b11110 H
b1111 "
b1111 (
b1111 *
b1111 ;
b1111 K
b110 G
1$
#4760
0$
#4780
06
b100 0
b100 <
b100 =
b1 G
1$
#4800
0$
#4820
1.
b10 G
1$
#4840
0$
#4860
b1011110 4
b1011110 8
b1011110 J
11
0.
b11110 "
b11110 (
b11110 *
b11110 ;
b11110 K
b1111011 ,
b1111011 9
b1111011 H
b1111110000000000 +
b1111110000000000 :
b11 G
1$
#4880
0$
#4900
b111110 4
b111110 8
b111110 J
01
b11110 )
b11110 I
b11110 L
b100 G
1$
#4920
0$
#4940
1-
1/
b101 G
1$
#4960
0$
#4980
b1 4
b1 8
b1 J
0-
0/
16
b111110 ,
b111110 9
b111110 H
b11111 "
b11111 (
b11111 *
b11111 ;
b11111 K
b110 G
1$
#5000
0$
#5020
06
b11 0
b11 <
b11 =
b1 G
1$
#5040
0$
#5060
1.
b10 G
1$
#5080
0$
#5100
b10111110 4
b10111110 8
b10111110 J
11
0.
b111110 "
b111110 (
b111110 *
b111110 ;
b111110 K
b11111011 ,
b11111011 9
b11111011 H
b1111000000000000 +
b1111000000000000 :
b11 G
1$
#5120
0$
#5140
b1111110 4
b1111110 8
b1111110 J
01
b111110 )
b111110 I
b111110 L
b100 G
1$
#5160
0$
#5180
1-
1/
b101 G
1$
#5200
0$
#5220
b1 4
b1 8
b1 J
0-
0/
16
b1111110 ,
b1111110 9
b1111110 H
b111111 "
b111111 (
b111111 *
b111111 ;
b111111 K
b110 G
1$
#5240
0$
#5260
06
b10 0
b10 <
b10 =
b1 G
1$
#5280
0$
#5300
1.
b10 G
1$
#5320
0$
#5340
b101111110 4
b101111110 8
b101111110 J
11
0.
b1111110 "
b1111110 (
b1111110 *
b1111110 ;
b1111110 K
b111111011 ,
b111111011 9
b111111011 H
b1100000000000000 +
b1100000000000000 :
b11 G
1$
#5360
0$
#5380
b11111110 4
b11111110 8
b11111110 J
01
b1111110 )
b1111110 I
b1111110 L
b100 G
1$
#5400
0$
#5420
1-
1/
b101 G
1$
#5440
0$
#5460
b1 4
b1 8
b1 J
0-
0/
16
b11111110 ,
b11111110 9
b11111110 H
b1111111 "
b1111111 (
b1111111 *
b1111111 ;
b1111111 K
b110 G
1$
#5480
0$
#5500
06
b1 0
b1 <
b1 =
b1 G
1$
#5520
0$
#5540
1.
b10 G
1$
#5560
0$
#5580
b1011111110 4
b1011111110 8
b1011111110 J
11
0.
b11111110 "
b11111110 (
b11111110 *
b11111110 ;
b11111110 K
b1111111011 ,
b1111111011 9
b1111111011 H
b0 +
b0 :
b11 G
1$
#5600
0$
#5620
01
b11111110 )
b11111110 I
b11111110 L
b100 G
1$
#5640
0$
#5660
1-
1/
b101 G
1$
#5680
0$
#5700
b1000000001 4
b1000000001 8
b1000000001 J
0-
0/
16
b1011111110 ,
b1011111110 9
b1011111110 H
b11111111 "
b11111111 (
b11111111 *
b11111111 ;
b11111111 K
b110 G
1$
#5720
0$
#5740
06
13
b0 0
b0 <
b0 =
b1 G
1$
#5760
0$
#5780
1!
b111 G
1$
#5800
0$
#5820
0!
12
b0 G
b1 F
1&
1$
b1 #
b1 '
b1 7
#5840
0$
#5860
15
b11111111111111111 4
b11111111111111111 8
b11111111111111111 J
b1 +
b1 :
b0 ,
b0 9
b0 H
b0 "
b0 (
b0 *
b0 ;
b0 K
b0 )
b0 I
b0 L
03
b1000 0
b1000 <
b1000 =
0&
1$
#5880
0$
#5900
b0 F
1%
1$
#5920
0$
#5940
02
b1 G
0%
1$
#5960
0$
#5980
1.
b10 G
1$
#6000
0$
#6020
11
0.
b100 +
b100 :
b11 G
1$
#6040
0$
#6060
01
b100 G
1$
#6080
0$
#6100
16
b110 G
1$
#6120
0$
#6140
06
b111 0
b111 <
b111 =
b1 G
1$
#6160
0$
#6180
1.
b10 G
1$
#6200
0$
#6220
11
0.
b10000 +
b10000 :
b11 G
1$
#6240
0$
#6260
01
b100 G
1$
#6280
0$
#6300
16
b110 G
1$
#6320
0$
#6340
06
b110 0
b110 <
b110 =
b1 G
1$
#6360
0$
#6380
1.
b10 G
1$
#6400
0$
#6420
11
0.
b1000000 +
b1000000 :
b11 G
1$
#6440
0$
#6460
01
b100 G
1$
#6480
0$
#6500
16
b110 G
1$
#6520
0$
#6540
06
b101 0
b101 <
b101 =
b1 G
1$
#6560
0$
#6580
1.
b10 G
1$
#6600
0$
#6620
11
0.
b100000000 +
b100000000 :
b11 G
1$
#6640
0$
#6660
01
b100 G
1$
#6680
0$
#6700
16
b110 G
1$
#6720
0$
#6740
06
b100 0
b100 <
b100 =
b1 G
1$
#6760
0$
#6780
1.
b10 G
1$
#6800
0$
#6820
11
0.
b10000000000 +
b10000000000 :
b11 G
1$
#6840
0$
#6860
01
b100 G
1$
#6880
0$
#6900
16
b110 G
1$
#6920
0$
#6940
06
b11 0
b11 <
b11 =
b1 G
1$
#6960
0$
#6980
1.
b10 G
1$
#7000
0$
#7020
11
0.
b1000000000000 +
b1000000000000 :
b11 G
1$
#7040
0$
#7060
01
b100 G
1$
#7080
0$
#7100
16
b110 G
1$
#7120
0$
#7140
06
b10 0
b10 <
b10 =
b1 G
1$
#7160
0$
#7180
1.
b10 G
1$
#7200
0$
#7220
11
0.
b100000000000000 +
b100000000000000 :
b11 G
1$
#7240
0$
#7260
01
b100 G
1$
#7280
0$
#7300
16
b110 G
1$
#7320
0$
#7340
06
b1 0
b1 <
b1 =
b1 G
1$
#7360
0$
#7380
1.
b10 G
1$
#7400
0$
#7420
05
b0 4
b0 8
b0 J
11
0.
b1 ,
b1 9
b1 H
b0 +
b0 :
b11 G
1$
#7440
0$
#7460
01
b100 G
1$
#7480
0$
#7500
1-
1/
b101 G
1$
#7520
0$
#7540
15
b11111111111111111 4
b11111111111111111 8
b11111111111111111 J
0-
0/
16
b0 ,
b0 9
b0 H
b1 "
b1 (
b1 *
b1 ;
b1 K
b110 G
1$
#7560
0$
#7580
06
13
b0 0
b0 <
b0 =
b1 G
1$
#7600
0$
#7620
1!
b111 G
1$
#7640
0$
#7660
b1 F
1$
