Entrega_Final/divisor/control.v
//modulo de control
module control (clk, rst, start, Zero, LessA, load, SHFT, update_A, set_Q, DEC, done);
    //entradas y salidas
    input clk;
    input rst;
    input start;
    input Zero;
    input LessA;
    output reg load;
    output reg SHFT;
    output reg update_A;
    output reg set_Q;
    output reg DEC;
    output reg done;

    // estados
    parameter init = 3'b000;
    parameter Check_Counter = 3'b001;
    parameter Shift = 3'b010;
    parameter Check_minor = 3'b011;
    parameter Substract = 3'b100;
    parameter Dec_Counter = 3'b101;
    parameter Done = 3'b110;

    //registro de estado
    reg [2:0] STATE;
    reg [4:0] count;

always @(posedge clk or posedge rst) 
begin
    if (rst)begin
        STATE <= init;
    end
    else
    begin
        case (STATE)
            init:
            begin
                count<=0;
                if (start) 
                    STATE = Check_Counter;
                else
                    STATE = init;
            end
            Check_Counter:
            begin
                if (Zero)
                    STATE = Done;
                else
                    STATE = Shift;
            end
            Shift:
            begin
                STATE = Check_minor;
            end
            Check_minor:
            begin
                if (LessA)
                    STATE = Dec_Counter;
                else
                    STATE = Substract;
            end
            Substract:
            begin
                STATE = Dec_Counter;
            end
            Dec_Counter:
            begin
                STATE = Check_Counter;
            end
            Done:
            begin
                count<=count+1;
                if (count >=28) 
                    STATE = init;
                else 
                    STATE = Done;
            end

            default: STATE = init;
        endcase    
    end
end
//activacion de salidas
always @(*) 
begin
    case (STATE)
        init:
        begin
            load = 1;
            SHFT = 0;
            update_A = 0;
            set_Q = 0;
            DEC = 0;
            done = 0;
        end 
        Check_Counter:
        begin
            load = 0;
            SHFT = 0;
            update_A = 0;
            set_Q = 0;
            DEC = 0;
            done = 0;
        end 
        Shift:
        begin
            load = 0;
            SHFT = 1;
            update_A = 0;
            set_Q = 0;
            DEC = 0;
            done = 0;   
        end
        Check_minor:
        begin
            load = 0;
            SHFT = 0;
            update_A = 0;
            set_Q = 0;
            DEC = 0;
            done = 0;   
        end
        Substract:
        begin
            load = 0;
            SHFT = 0;
            update_A = 1;
            set_Q = 1;
            DEC = 0;
            done = 0; 
        end
        Dec_Counter:
        begin
            load = 0;
            SHFT = 0;
            update_A = 0;
            set_Q = 0;
            DEC = 1;
            done = 0; 
        end
        Done:
        begin
            load = 0;
            SHFT = 0;
            update_A = 0;
            set_Q = 0;
            DEC = 0;
            done = 1; 
        end
        default: 
        begin
            load = 0;
            SHFT = 0;
            update_A = 0;
            set_Q = 0;
            DEC = 0;
            done = 0; 
        end
    endcase
end

endmodule

Entrega_Final/divisor/compMinor.v
// Comparador de A<M
module compMinor (A, M , LessA);
    //entradas y salida
    input [16:0] A;
    input [15:0] M;
    output LessA;

    //comparación
    assign LessA = (A < {1'b0,M});

endmodule

Entrega_Final/divisor/compZero.v
//comparador para determinar si el contador terminó
module compZero (Out_C, Zero);
    //entrada y salida
    input [4:0]Out_C;
    output Zero;
    //comparación
    assign Zero = (Out_C == 0);
endmodule

Entrega_Final/divisor/Counter.v
//contador descendente
module Counter (clk, load, DEC, Out_C);

//señales de control
input clk;
input load;
input DEC;

//salida
output reg [4:0]Out_C; // como el número es de máximo 16 bits por ahora entonces el contador solo necesita 5 bits

always @(posedge clk) 
begin
    if (load)
        Out_C <= 5'd16; 
    else if(DEC)
        Out_C <= Out_C - 1;
        
end
    
endmodule

Entrega_Final/divisor/subtractor.v
//restador suma complemento a 2
module subtractor (A, M, A_sub);
    // entradas y Salidas
    input [16:0] A;
    input [15:0] M;
    output [16:0] A_sub;
    
    //complemento a 2
    wire [16:0] comp2_M;
    assign comp2_M = ~{1'b0,M} + 1'b1;
    assign A_sub = A + comp2_M;
    
endmodule

Entrega_Final/divisor/regAQ.v
// registro combinado AQ
module regAQ (clk, set_Q, load, SHFT, update_A, in_Q, A_sub, A, Q);

    //Señales de control
    input clk;
    input set_Q;
    input load;
    input SHFT;
    input update_A;
    //Entradas
    input [15:0] in_Q;
    input [16:0] A_sub;
    //Salidas
    output reg[16:0] A;
    output reg[15:0] Q;

always @(posedge clk) 
begin
    if (load) 
    begin
        A <= 17'b0;
        Q <= in_Q;   
    end
    else if (SHFT) 
    begin
        {A,Q} <= {A,Q} <<1;   
    end
    else 
    begin
        if (update_A) 
            A <= A_sub;
        if (set_Q)
            Q[0] <= 1'b1;
    end
end

endmodule

Entrega_Final/divisor/divisor.v
module divisor (clk, rst, start, Q, M, Cociente, Residuo, done);
//entradas y salidas
input clk;
input rst;
input start;
input [15:0] Q;
input [15:0] M;
output [15:0] Cociente;
output [16:0] Residuo;
output done;

// señales de control 
wire load;
wire SHFT;
wire update_A;
wire set_Q;
wire DEC;

wire [16:0] w_A;
wire [15:0] w_Q;
wire [16:0] A_sub;
wire [4:0] Out_C;
wire Zero;
wire LessA;

regAQ AQ0(.clk(clk), .set_Q(set_Q), .load(load), .SHFT(SHFT), .update_A(update_A), .in_Q(Q), .A_sub(A_sub), .A(w_A), .Q(w_Q));
subtractor sub0(.A(w_A), .M(M), .A_sub(A_sub));
Counter c0(.clk(clk), .load(load), .DEC(DEC), .Out_C(Out_C));
compZero czero0(.Out_C(Out_C), .Zero(Zero));
compMinor cminor0(.A(w_A), .M(M) , .LessA(LessA));
control ctrl0(.clk(clk), .rst(rst), .start(start), .Zero(Zero), .LessA(LessA), .load(load), .SHFT(SHFT), .update_A(update_A), .set_Q(set_Q), .DEC(DEC), .done(done));
assign Residuo = w_A;
assign Cociente = w_Q;


endmodule

Entrega_Final/divisor/divisor_TB.v
module divisor_TB;

    reg clk;
    reg rst;
    reg start;
    reg [15:0] Q;
    reg [15:0] M;
    wire [15:0] Cociente;
    wire [16:0] Residuo;
    wire done;

divisor uut(.clk(clk), .rst(rst), .start(start), .Q(Q), .M(M), .Cociente(Cociente), .Residuo(Residuo), .done(done));
initial begin
    clk=0;
    forever #20 clk = ~clk;
end
initial begin
    $dumpfile("divisor_TB.vcd");
    $dumpvars(0, divisor_TB);

    rst =1;
    start = 0;
    Q = 0;
    M = 0;

    @(posedge clk);
    rst=0;

    Q=16'd99;
    M=16'd3;
    start=1;
    @(posedge clk);
    start=0;

    wait(done);
    @(posedge clk);
    rst=1;
    @(posedge clk);
    rst=0;

    Q=16'd111;
    M=16'd2;
    start=1;
    @(posedge clk);
    start=0;
    wait(done);
    repeat(2) @(posedge clk);
    $finish;
end

endmodule

Entrega_Final/divisor/divisor_TB.vcd
$date
	Thu Jul 16 10:55:02 2026
$end
$version
	Icarus Verilog
$end
$timescale
	1s
$end
$scope module divisor_TB $end
$var wire 1 ! done $end
$var wire 17 " Residuo [16:0] $end
$var wire 16 # Cociente [15:0] $end
$var reg 16 $ M [15:0] $end
$var reg 16 % Q [15:0] $end
$var reg 1 & clk $end
$var reg 1 ' rst $end
$var reg 1 ( start $end
$scope module uut $end
$var wire 16 ) Cociente [15:0] $end
$var wire 16 * M [15:0] $end
$var wire 16 + Q [15:0] $end
$var wire 17 , Residuo [16:0] $end
$var wire 1 & clk $end
$var wire 1 ' rst $end
$var wire 1 ( start $end
$var wire 16 - w_Q [15:0] $end
$var wire 17 . w_A [16:0] $end
$var wire 1 / update_A $end
$var wire 1 0 set_Q $end
$var wire 1 1 load $end
$var wire 1 ! done $end
$var wire 1 2 Zero $end
$var wire 1 3 SHFT $end
$var wire 5 4 Out_C [4:0] $end
$var wire 1 5 LessA $end
$var wire 1 6 DEC $end
$var wire 17 7 A_sub [16:0] $end
$scope module AQ0 $end
$var wire 1 & clk $end
$var wire 16 8 in_Q [15:0] $end
$var wire 1 / update_A $end
$var wire 1 0 set_Q $end
$var wire 1 1 load $end
$var wire 1 3 SHFT $end
$var wire 17 9 A_sub [16:0] $end
$var reg 17 : A [16:0] $end
$var reg 16 ; Q [15:0] $end
$upscope $end
$scope module c0 $end
$var wire 1 & clk $end
$var wire 1 1 load $end
$var wire 1 6 DEC $end
$var reg 5 < Out_C [4:0] $end
$upscope $end
$scope module cminor0 $end
$var wire 17 = A [16:0] $end
$var wire 16 > M [15:0] $end
$var wire 1 5 LessA $end
$upscope $end
$scope module ctrl0 $end
$var wire 1 5 LessA $end
$var wire 1 & clk $end
$var wire 1 ' rst $end
$var wire 1 ( start $end
$var wire 1 2 Zero $end
$var parameter 3 ? Check_Counter $end
$var parameter 3 @ Check_minor $end
$var parameter 3 A Dec_Counter $end
$var parameter 3 B Done $end
$var parameter 3 C Shift $end
$var parameter 3 D Substract $end
$var parameter 3 E init $end
$var reg 1 6 DEC $end
$var reg 1 3 SHFT $end
$var reg 3 F STATE [2:0] $end
$var reg 5 G count [4:0] $end
$var reg 1 ! done $end
$var reg 1 1 load $end
$var reg 1 0 set_Q $end
$var reg 1 / update_A $end
$upscope $end
$scope module czero0 $end
$var wire 5 H Out_C [4:0] $end
$var wire 1 2 Zero $end
$upscope $end
$scope module sub0 $end
$var wire 17 I A [16:0] $end
$var wire 16 J M [15:0] $end
$var wire 17 K comp2_M [16:0] $end
$var wire 17 L A_sub [16:0] $end
$upscope $end
$upscope $end
$upscope $end
$enddefinitions $end
$comment Show the parameter values. $end
$dumpall
b0 E
b100 D
b10 C
b110 B
b101 A
b11 @
b1 ?
$end
#0
$dumpvars
bx L
b0 K
b0 J
bx I
bx H
bx G
b0 F
b0 >
bx =
bx <
bx ;
bx :
bx 9
b0 8
bx 7
06
x5
bx 4
03
x2
11
00
0/
bx .
bx -
bx ,
b0 +
b0 *
bx )
0(
1'
0&
b0 %
b0 $
bx #
bx "
0!
$end
#20
b1100011 #
b1100011 )
b1100011 -
b1100011 ;
15
b11111111111111101 7
b11111111111111101 9
b11111111111111101 L
b0 "
b0 ,
b0 .
b0 :
b0 =
b0 I
02
b10000 4
b10000 <
b10000 H
b11111111111111101 K
1(
b11 $
b11 *
b11 >
b11 J
b1100011 %
b1100011 +
b1100011 8
0'
1&
#40
0&
#60
b0 G
01
0(
b1 F
1&
#80
0&
#100
13
b10 F
1&
#120
0&
#140
b11000110 #
b11000110 )
b11000110 -
b11000110 ;
03
b11 F
1&
#160
0&
#180
16
b101 F
1&
#200
0&
#220
b1111 4
b1111 <
b1111 H
06
b1 F
1&
#240
0&
#260
13
b10 F
1&
#280
0&
#300
b110001100 #
b110001100 )
b110001100 -
b110001100 ;
03
b11 F
1&
#320
0&
#340
16
b101 F
1&
#360
0&
#380
b1110 4
b1110 <
b1110 H
06
b1 F
1&
#400
0&
#420
13
b10 F
1&
#440
0&
#460
b1100011000 #
b1100011000 )
b1100011000 -
b1100011000 ;
03
b11 F
1&
#480
0&
#500
16
b101 F
1&
#520
0&
#540
b1101 4
b1101 <
b1101 H
06
b1 F
1&
#560
0&
#580
13
b10 F
1&
#600
0&
#620
b11000110000 #
b11000110000 )
b11000110000 -
b11000110000 ;
03
b11 F
1&
#640
0&
#660
16
b101 F
1&
#680
0&
#700
b1100 4
b1100 <
b1100 H
06
b1 F
1&
#720
0&
#740
13
b10 F
1&
#760
0&
#780
b110001100000 #
b110001100000 )
b110001100000 -
b110001100000 ;
03
b11 F
1&
#800
0&
#820
16
b101 F
1&
#840
0&
#860
b1011 4
b1011 <
b1011 H
06
b1 F
1&
#880
0&
#900
13
b10 F
1&
#920
0&
#940
b1100011000000 #
b1100011000000 )
b1100011000000 -
b1100011000000 ;
03
b11 F
1&
#960
0&
#980
16
b101 F
1&
#1000
0&
#1020
b1010 4
b1010 <
b1010 H
06
b1 F
1&
#1040
0&
#1060
13
b10 F
1&
#1080
0&
#1100
b11000110000000 #
b11000110000000 )
b11000110000000 -
b11000110000000 ;
03
b11 F
1&
#1120
0&
#1140
16
b101 F
1&
#1160
0&
#1180
b1001 4
b1001 <
b1001 H
06
b1 F
1&
#1200
0&
#1220
13
b10 F
1&
#1240
0&
#1260
b110001100000000 #
b110001100000000 )
b110001100000000 -
b110001100000000 ;
03
b11 F
1&
#1280
0&
#1300
16
b101 F
1&
#1320
0&
#1340
b1000 4
b1000 <
b1000 H
06
b1 F
1&
#1360
0&
#1380
13
b10 F
1&
#1400
0&
#1420
b1100011000000000 #
b1100011000000000 )
b1100011000000000 -
b1100011000000000 ;
03
b11 F
1&
#1440
0&
#1460
16
b101 F
1&
#1480
0&
#1500
b111 4
b111 <
b111 H
06
b1 F
1&
#1520
0&
#1540
13
b10 F
1&
#1560
0&
#1580
b11111111111111110 7
b11111111111111110 9
b11111111111111110 L
b1 "
b1 ,
b1 .
b1 :
b1 =
b1 I
b1000110000000000 #
b1000110000000000 )
b1000110000000000 -
b1000110000000000 ;
03
b11 F
1&
#1600
0&
#1620
16
b101 F
1&
#1640
0&
#1660
b110 4
b110 <
b110 H
06
b1 F
1&
#1680
0&
#1700
13
b10 F
1&
#1720
0&
#1740
05
b0 7
b0 9
b0 L
b11 "
b11 ,
b11 .
b11 :
b11 =
b11 I
b1100000000000 #
b1100000000000 )
b1100000000000 -
b1100000000000 ;
03
b11 F
1&
#1760
0&
#1780
10
1/
b100 F
1&
#1800
0&
#1820
b1100000000001 #
b1100000000001 )
b1100000000001 -
b1100000000001 ;
15
b11111111111111101 7
b11111111111111101 9
b11111111111111101 L
b0 "
b0 ,
b0 .
b0 :
b0 =
b0 I
16
00
0/
b101 F
1&
#1840
0&
#1860
b101 4
b101 <
b101 H
06
b1 F
1&
#1880
0&
#1900
13
b10 F
1&
#1920
0&
#1940
b11000000000010 #
b11000000000010 )
b11000000000010 -
b11000000000010 ;
03
b11 F
1&
#1960
0&
#1980
16
b101 F
1&
#2000
0&
#2020
b100 4
b100 <
b100 H
06
b1 F
1&
#2040
0&
#2060
13
b10 F
1&
#2080
0&
#2100
b110000000000100 #
b110000000000100 )
b110000000000100 -
b110000000000100 ;
03
b11 F
1&
#2120
0&
#2140
16
b101 F
1&
#2160
0&
#2180
b11 4
b11 <
b11 H
06
b1 F
1&
#2200
0&
#2220
13
b10 F
1&
#2240
0&
#2260
b1100000000001000 #
b1100000000001000 )
b1100000000001000 -
b1100000000001000 ;
03
b11 F
1&
#2280
0&
#2300
16
b101 F
1&
#2320
0&
#2340
b10 4
b10 <
b10 H
06
b1 F
1&
#2360
0&
#2380
13
b10 F
1&
#2400
0&
#2420
b11111111111111110 7
b11111111111111110 9
b11111111111111110 L
b1 "
b1 ,
b1 .
b1 :
b1 =
b1 I
b1000000000010000 #
b1000000000010000 )
b1000000000010000 -
b1000000000010000 ;
03
b11 F
1&
#2440
0&
#2460
16
b101 F
1&
#2480
0&
#2500
b1 4
b1 <
b1 H
06
b1 F
1&
#2520
0&
#2540
13
b10 F
1&
#2560
0&
#2580
05
b0 7
b0 9
b0 L
b11 "
b11 ,
b11 .
b11 :
b11 =
b11 I
b100000 #
b100000 )
b100000 -
b100000 ;
03
b11 F
1&
#2600
0&
#2620
10
1/
b100 F
1&
#2640
0&
#2660
b100001 #
b100001 )
b100001 -
b100001 ;
15
b11111111111111101 7
b11111111111111101 9
b11111111111111101 L
b0 "
b0 ,
b0 .
b0 :
b0 =
b0 I
16
00
0/
b101 F
1&
#2680
0&
#2700
12
b0 4
b0 <
b0 H
06
b1 F
1&
#2720
0&
#2740
1!
b110 F
1&
#2760
0&
#2780
0!
11
b0 F
b1 G
1'
1&
#2800
0&
#2820
b1100011 #
b1100011 )
b1100011 -
b1100011 ;
02
b10000 4
b10000 <
b10000 H
b11111111111111110 7
b11111111111111110 9
b11111111111111110 L
b11111111111111110 K
1(
b10 $
b10 *
b10 >
b10 J
b1101111 %
b1101111 +
b1101111 8
0'
1&
#2840
0&
#2860
b1101111 #
b1101111 )
b1101111 -
b1101111 ;
b0 G
01
0(
b1 F
1&
#2880
0&
#2900
13
b10 F
1&
#2920
0&
#2940
b11011110 #
b11011110 )
b11011110 -
b11011110 ;
03
b11 F
1&
#2960
0&
#2980
16
b101 F
1&
#3000
0&
#3020
b1111 4
b1111 <
b1111 H
06
b1 F
1&
#3040
0&
#3060
13
b10 F
1&
#3080
0&
#3100
b110111100 #
b110111100 )
b110111100 -
b110111100 ;
03
b11 F
1&
#3120
0&
#3140
16
b101 F
1&
#3160
0&
#3180
b1110 4
b1110 <
b1110 H
06
b1 F
1&
#3200
0&
#3220
13
b10 F
1&
#3240
0&
#3260
b1101111000 #
b1101111000 )
b1101111000 -
b1101111000 ;
03
b11 F
1&
#3280
0&
#3300
16
b101 F
1&
#3320
0&
#3340
b1101 4
b1101 <
b1101 H
06
b1 F
1&
#3360
0&
#3380
13
b10 F
1&
#3400
0&
#3420
b11011110000 #
b11011110000 )
b11011110000 -
b11011110000 ;
03
b11 F
1&
#3440
0&
#3460
16
b101 F
1&
#3480
0&
#3500
b1100 4
b1100 <
b1100 H
06
b1 F
1&
#3520
0&
#3540
13
b10 F
1&
#3560
0&
#3580
b110111100000 #
b110111100000 )
b110111100000 -
b110111100000 ;
03
b11 F
1&
#3600
0&
#3620
16
b101 F
1&
#3640
0&
#3660
b1011 4
b1011 <
b1011 H
06
b1 F
1&
#3680
0&
#3700
13
b10 F
1&
#3720
0&
#3740
b1101111000000 #
b1101111000000 )
b1101111000000 -
b1101111000000 ;
03
b11 F
1&
#3760
0&
#3780
16
b101 F
1&
#3800
0&
#3820
b1010 4
b1010 <
b1010 H
06
b1 F
1&
#3840
0&
#3860
13
b10 F
1&
#3880
0&
#3900
b11011110000000 #
b11011110000000 )
b11011110000000 -
b11011110000000 ;
03
b11 F
1&
#3920
0&
#3940
16
b101 F
1&
#3960
0&
#3980
b1001 4
b1001 <
b1001 H
06
b1 F
1&
#4000
0&
#4020
13
b10 F
1&
#4040
0&
#4060
b110111100000000 #
b110111100000000 )
b110111100000000 -
b110111100000000 ;
03
b11 F
1&
#4080
0&
#4100
16
b101 F
1&
#4120
0&
#4140
b1000 4
b1000 <
b1000 H
06
b1 F
1&
#4160
0&
#4180
13
b10 F
1&
#4200
0&
#4220
b1101111000000000 #
b1101111000000000 )
b1101111000000000 -
b1101111000000000 ;
03
b11 F
1&
#4240
0&
#4260
16
b101 F
1&
#4280
0&
#4300
b111 4
b111 <
b111 H
06
b1 F
1&
#4320
0&
#4340
13
b10 F
1&
#4360
0&
#4380
b11111111111111111 7
b11111111111111111 9
b11111111111111111 L
b1 "
b1 ,
b1 .
b1 :
b1 =
b1 I
b1011110000000000 #
b1011110000000000 )
b1011110000000000 -
b1011110000000000 ;
03
b11 F
1&
#4400
0&
#4420
16
b101 F
1&
#4440
0&
#4460
b110 4
b110 <
b110 H
06
b1 F
1&
#4480
0&
#4500
13
b10 F
1&
#4520
0&
#4540
05
b1 7
b1 9
b1 L
b11 "
b11 ,
b11 .
b11 :
b11 =
b11 I
b111100000000000 #
b111100000000000 )
b111100000000000 -
b111100000000000 ;
03
b11 F
1&
#4560
0&
#4580
10
1/
b100 F
1&
#4600
0&
#4620
b111100000000001 #
b111100000000001 )
b111100000000001 -
b111100000000001 ;
15
b11111111111111111 7
b11111111111111111 9
b11111111111111111 L
b1 "
b1 ,
b1 .
b1 :
b1 =
b1 I
16
00
0/
b101 F
1&
#4640
0&
#4660
b101 4
b101 <
b101 H
06
b1 F
1&
#4680
0&
#4700
13
b10 F
1&
#4720
0&
#4740
05
b0 7
b0 9
b0 L
b10 "
b10 ,
b10 .
b10 :
b10 =
b10 I
b1111000000000010 #
b1111000000000010 )
b1111000000000010 -
b1111000000000010 ;
03
b11 F
1&
#4760
0&
#4780
10
1/
b100 F
1&
#4800
0&
#4820
b1111000000000011 #
b1111000000000011 )
b1111000000000011 -
b1111000000000011 ;
15
b11111111111111110 7
b11111111111111110 9
b11111111111111110 L
b0 "
b0 ,
b0 .
b0 :
b0 =
b0 I
16
00
0/
b101 F
1&
#4840
0&
#4860
b100 4
b100 <
b100 H
06
b1 F
1&
#4880
0&
#4900
13
b10 F
1&
#4920
0&
#4940
b11111111111111111 7
b11111111111111111 9
b11111111111111111 L
b1 "
b1 ,
b1 .
b1 :
b1 =
b1 I
b1110000000000110 #
b1110000000000110 )
b1110000000000110 -
b1110000000000110 ;
03
b11 F
1&
#4960
0&
#4980
16
b101 F
1&
#5000
0&
#5020
b11 4
b11 <
b11 H
06
b1 F
1&
#5040
0&
#5060
13
b10 F
1&
#5080
0&
#5100
05
b1 7
b1 9
b1 L
b11 "
b11 ,
b11 .
b11 :
b11 =
b11 I
b1100000000001100 #
b1100000000001100 )
b1100000000001100 -
b1100000000001100 ;
03
b11 F
1&
#5120
0&
#5140
10
1/
b100 F
1&
#5160
0&
#5180
b1100000000001101 #
b1100000000001101 )
b1100000000001101 -
b1100000000001101 ;
15
b11111111111111111 7
b11111111111111111 9
b11111111111111111 L
b1 "
b1 ,
b1 .
b1 :
b1 =
b1 I
16
00
0/
b101 F
1&
#5200
0&
#5220
b10 4
b10 <
b10 H
06
b1 F
1&
#5240
0&
#5260
13
b10 F
1&
#5280
0&
#5300
05
b1 7
b1 9
b1 L
b11 "
b11 ,
b11 .
b11 :
b11 =
b11 I
b1000000000011010 #
b1000000000011010 )
b1000000000011010 -
b1000000000011010 ;
03
b11 F
1&
#5320
0&
#5340
10
1/
b100 F
1&
#5360
0&
#5380
b1000000000011011 #
b1000000000011011 )
b1000000000011011 -
b1000000000011011 ;
15
b11111111111111111 7
b11111111111111111 9
b11111111111111111 L
b1 "
b1 ,
b1 .
b1 :
b1 =
b1 I
16
00
0/
b101 F
1&
#5400
0&
#5420
b1 4
b1 <
b1 H
06
b1 F
1&
#5440
0&
#5460
13
b10 F
1&
#5480
0&
#5500
05
b1 7
b1 9
b1 L
b11 "
b11 ,
b11 .
b11 :
b11 =
b11 I
b110110 #
b110110 )
b110110 -
b110110 ;
03
b11 F
1&
#5520
0&
#5540
10
1/
b100 F
1&
#5560
0&
#5580
b110111 #
b110111 )
b110111 -
b110111 ;
15
b11111111111111111 7
b11111111111111111 9
b11111111111111111 L
b1 "
b1 ,
b1 .
b1 :
b1 =
b1 I
16
00
0/
b101 F
1&
#5600
0&
#5620
12
b0 4
b0 <
b0 H
06
b1 F
1&
#5640
0&
#5660
1!
b110 F
1&
#5680
0&
#5700
b1 G
1&
#5720
0&
#5740
b10 G
1&
