Entrega_Final/paridad/control.v
module control (clk, rst, init, Zero, LSB, Load, SHFT, DEC, INC, done);
input clk;
input rst;
input init;
input Zero;
input LSB;
output reg Load;
output reg SHFT;
output reg DEC;
output reg INC;
output reg done;

parameter Start = 3'b000;
parameter Check_counter = 3'b001;
parameter Check_lsb = 3'b010;
parameter inc_reg = 3'b011;
parameter shift_dec = 3'b100;
parameter Finish = 3'b101;

reg [2:0] STATE;
reg [4:0] Count;

always @(posedge clk or posedge rst) 
begin
    if (rst)
        STATE <= Start;
    else begin
        case (STATE)
            Start:
            begin
                Count <= 0;
                if(init)
                    STATE <= Check_counter;
                else
                    STATE <= Start; 
            end 
            Check_counter:
            begin
                if(Zero)
                    STATE <= Finish;
                else
                    STATE <= Check_lsb; 
            end
            Check_lsb:
            begin
                if(LSB)
                    STATE <= inc_reg;
                else
                    STATE <= shift_dec;  
            end
            inc_reg:
            begin
                STATE <= shift_dec;
            end
            shift_dec:
            begin
                STATE <= Check_counter;
            end
            Finish:
            begin
                Count <= Count+1;
                if (Count >= 28) 
                    STATE <= Start;
                else
                    STATE <= Finish;
            end
            default:
                STATE <= Start;
        endcase
    end 
end
always @(*) 
begin
    case (STATE)
        Start:
        begin
            SHFT=0;
            Load=1;
            DEC=0;
            INC=0;
            done=0;
        end
        Check_counter:
        begin
            SHFT=0;
            Load=0;
            DEC=0;
            INC=0;
            done=0;
        end
        Check_lsb:
        begin
            SHFT=0;
            Load=0;
            DEC=0;
            INC=0;
            done=0;
        end
        inc_reg:
        begin
            SHFT=0;
            Load=0;
            DEC=0;
            INC=1;
            done=0;
        end
        shift_dec:
        begin
            SHFT=1;
            Load=0;
            DEC=1;
            INC=0;
            done=0;
        end
        Finish:
        begin
            SHFT=0;
            Load=0;
            DEC=0;
            INC=0;
            done=1;
        end
        default:
        begin
            SHFT=0;
            Load=0;
            DEC=0;
            INC=0;
            done=0;
        end
    endcase    
end
`ifdef BENCH
reg [8*20:1] estados;
always @(*) begin
    case (STATE)
        Start: estados="START";
        Check_lsb: estados="CHECK_LSB";
        Check_counter: estados="CHECK_COUNTER";
        inc_reg: estados="INC_REG";
        shift_dec: estados="SHIFT_DEC";
        Finish: estados="FINISH";
        default: estados="unknown";
    endcase
end
`endif
endmodule

Entrega_Final/paridad/counter.v
module counter (clk, Load, DEC, Zero);
input clk;
input Load;
input DEC;
output Zero;
reg [3:0] counter;
assign Zero = (counter==0);
always @(posedge clk) 
begin
    if (Load) 
    begin
        counter <= 4'd9;    
    end
    else if (DEC) 
    begin
        counter <= counter - 1;    
    end
end
endmodule

Entrega_Final/paridad/onesCount.v
module onesCount(clk, Load, INC, parity, bits1);
input clk;
input Load;
input INC;
output parity;
output [3:0]bits1;
reg [3:0]onesCount;
assign bits1 = onesCount;
assign parity = onesCount[0];

always @(posedge clk) 
begin
    if (Load) 
    begin
        onesCount <= 4'b0;
    end
    else if (INC) 
    begin
        onesCount <= onesCount+1;    
    end
end    
endmodule

Entrega_Final/paridad/regA.v
module regA (clk, Load, SHFT, in_bits, LSB);
input clk;
input Load;
input SHFT;
input [8:0] in_bits;
output LSB;
reg [8:0] regA;
assign LSB = regA[0];

always @(posedge clk) begin
    if (Load) 
    begin
        regA <= in_bits;    
    end
    else if (SHFT) 
    begin
        regA <= regA>>1;    
    end
end
    
endmodule

Entrega_Final/paridad/parity.v
module parity (clk, rst, init, in_bits, bits1, parity, done);
input rst;
input clk;
input init;
input [8:0]in_bits;
output [3:0]bits1;
output parity;
output done;

wire Load;
wire SHFT;
wire DEC;
wire INC;
wire Zero;
wire LSB;

regA regA0(.clk(clk), .Load(Load), .SHFT(SHFT), .in_bits(in_bits), .LSB(LSB));
onesCount onesCount0(.clk(clk), .Load(Load), .INC(INC), .parity(parity), .bits1(bits1));
counter counter0(.clk(clk), .Load(Load), .DEC(DEC), .Zero(Zero));
control control0(.clk(clk), .rst(rst), .init(init), .Zero(Zero), .LSB(LSB), .Load(Load), .SHFT(SHFT), .DEC(DEC), .INC(INC), .done(done));

endmodule

Entrega_Final/paridad/parity_TB.v
module parity_TB;
reg rst;
reg clk;
reg init;
reg [8:0]in_bits;
wire [3:0]bits1;
wire parity;
wire done;

parity uut(.clk(clk), .rst(rst), .init(init), .in_bits(in_bits), .bits1(bits1), .parity(parity), .done(done));
initial begin
    clk=0;
    forever #20 clk=~clk;
end
initial begin
    $dumpfile("parity_TB.vcd");
    $dumpvars(0,parity_TB);

    init=0;
    rst=1;
    in_bits=9'b000000000;
    @(posedge clk);
    rst=0;
    init=1;
    @(posedge clk);
    init=0;
    wait(done);
    #40;
    @(posedge clk);
    rst=1;
    in_bits=9'b111111111;
    @(posedge clk);
    rst=0;
    init=1;
    @(posedge clk);
    init=0;
    wait(done);
    #40;
    @(posedge clk);
    rst=1;
    in_bits=9'b101010101;
    @(posedge clk);
    rst=0;
    init=1;
    @(posedge clk);
    init=0;
    wait(done);
    #40;
    @(posedge clk);
    rst=1;
    in_bits=9'b111100000;
    @(posedge clk);
    rst=0;
    init=1;
    @(posedge clk);
    init=0;
    wait(done);
    #40;
    @(posedge clk);
    rst=1;
    in_bits=9'b100000000;
    @(posedge clk);
    rst=0;
    init=1;
    @(posedge clk);
    init=0;
    wait(done);
    #40;
    $finish;
end


endmodule

Entrega_Final/paridad/parity_TB.vcd
$date
	Mon Jun 29 01:47:58 2026
$end
$version
	Icarus Verilog
$end
$timescale
	1s
$end
$scope module parity_TB $end
$var wire 1 ! parity $end
$var wire 1 " done $end
$var wire 4 # bits1 [3:0] $end
$var reg 1 $ clk $end
$var reg 9 % in_bits [8:0] $end
$var reg 1 & init $end
$var reg 1 ' rst $end
$scope module uut $end
$var wire 1 $ clk $end
$var wire 9 ( in_bits [8:0] $end
$var wire 1 & init $end
$var wire 1 ' rst $end
$var wire 1 ! parity $end
$var wire 1 " done $end
$var wire 4 ) bits1 [3:0] $end
$var wire 1 * Zero $end
$var wire 1 + SHFT $end
$var wire 1 , Load $end
$var wire 1 - LSB $end
$var wire 1 . INC $end
$var wire 1 / DEC $end
$scope module control0 $end
$var wire 1 $ clk $end
$var wire 1 & init $end
$var wire 1 ' rst $end
$var wire 1 * Zero $end
$var wire 1 - LSB $end
$var parameter 3 0 Check_counter $end
$var parameter 3 1 Check_lsb $end
$var parameter 3 2 Finish $end
$var parameter 3 3 Start $end
$var parameter 3 4 inc_reg $end
$var parameter 3 5 shift_dec $end
$var reg 5 6 Count [4:0] $end
$var reg 1 / DEC $end
$var reg 1 . INC $end
$var reg 1 , Load $end
$var reg 1 + SHFT $end
$var reg 3 7 STATE [2:0] $end
$var reg 1 " done $end
$var reg 160 8 estados [160:1] $end
$upscope $end
$scope module counter0 $end
$var wire 1 / DEC $end
$var wire 1 , Load $end
$var wire 1 $ clk $end
$var wire 1 * Zero $end
$var reg 4 9 counter [3:0] $end
$upscope $end
$scope module onesCount0 $end
$var wire 1 . INC $end
$var wire 1 , Load $end
$var wire 4 : bits1 [3:0] $end
$var wire 1 $ clk $end
$var wire 1 ! parity $end
$var reg 4 ; onesCount [3:0] $end
$upscope $end
$scope module regA0 $end
$var wire 1 , Load $end
$var wire 1 + SHFT $end
$var wire 1 $ clk $end
$var wire 9 < in_bits [8:0] $end
$var wire 1 - LSB $end
$var reg 9 = regA [8:0] $end
$upscope $end
$upscope $end
$upscope $end
$enddefinitions $end
$comment Show the parameter values. $end
$dumpall
b100 5
b11 4
b0 3
b101 2
b10 1
b1 0
$end
#0
$dumpvars
bx =
b0 <
bx ;
bx :
bx 9
b101001101010100010000010101001001010100 8
b0 7
bx 6
0/
0.
x-
1,
0+
x*
bx )
b0 (
1'
0&
b0 %
0$
bx #
0"
x!
$end
#20
0,
b1000011010010000100010101000011010010110101111101000011010011110101010101001110010101000100010101010010 8
0-
0!
b1 7
b0 6
b0 =
b0 #
b0 )
b0 :
b0 ;
0*
b1001 9
1&
0'
1$
#40
0$
#60
b10000110100100001000101010000110100101101011111010011000101001101000010 8
b10 7
0&
1$
#80
0$
#100
1/
1+
b10100110100100001001001010001100101010001011111010001000100010101000011 8
b100 7
1$
#120
0$
#140
b1000011010010000100010101000011010010110101111101000011010011110101010101001110010101000100010101010010 8
0/
0+
b1 7
b1000 9
1$
#160
0$
#180
b10000110100100001000101010000110100101101011111010011000101001101000010 8
b10 7
1$
#200
0$
#220
b10100110100100001001001010001100101010001011111010001000100010101000011 8
1/
1+
b100 7
1$
#240
0$
#260
0/
0+
b1000011010010000100010101000011010010110101111101000011010011110101010101001110010101000100010101010010 8
b1 7
b111 9
1$
#280
0$
#300
b10000110100100001000101010000110100101101011111010011000101001101000010 8
b10 7
1$
#320
0$
#340
1/
1+
b10100110100100001001001010001100101010001011111010001000100010101000011 8
b100 7
1$
#360
0$
#380
b1000011010010000100010101000011010010110101111101000011010011110101010101001110010101000100010101010010 8
0/
0+
b1 7
b110 9
1$
#400
0$
#420
b10000110100100001000101010000110100101101011111010011000101001101000010 8
b10 7
1$
#440
0$
#460
b10100110100100001001001010001100101010001011111010001000100010101000011 8
1/
1+
b100 7
1$
#480
0$
#500
0/
0+
b1000011010010000100010101000011010010110101111101000011010011110101010101001110010101000100010101010010 8
b1 7
b101 9
1$
#520
0$
#540
b10000110100100001000101010000110100101101011111010011000101001101000010 8
b10 7
1$
#560
0$
#580
1/
1+
b10100110100100001001001010001100101010001011111010001000100010101000011 8
b100 7
1$
#600
0$
#620
b1000011010010000100010101000011010010110101111101000011010011110101010101001110010101000100010101010010 8
0/
0+
b1 7
b100 9
1$
#640
0$
#660
b10000110100100001000101010000110100101101011111010011000101001101000010 8
b10 7
1$
#680
0$
#700
b10100110100100001001001010001100101010001011111010001000100010101000011 8
1/
1+
b100 7
1$
#720
0$
#740
0/
0+
b1000011010010000100010101000011010010110101111101000011010011110101010101001110010101000100010101010010 8
b1 7
b11 9
1$
#760
0$
#780
b10000110100100001000101010000110100101101011111010011000101001101000010 8
b10 7
1$
#800
0$
#820
1/
1+
b10100110100100001001001010001100101010001011111010001000100010101000011 8
b100 7
1$
#840
0$
#860
b1000011010010000100010101000011010010110101111101000011010011110101010101001110010101000100010101010010 8
0/
0+
b1 7
b10 9
1$
#880
0$
#900
b10000110100100001000101010000110100101101011111010011000101001101000010 8
b10 7
1$
#920
0$
#940
b10100110100100001001001010001100101010001011111010001000100010101000011 8
1/
1+
b100 7
1$
#960
0$
#980
0/
0+
b1000011010010000100010101000011010010110101111101000011010011110101010101001110010101000100010101010010 8
b1 7
b1 9
1$
#1000
0$
#1020
b10000110100100001000101010000110100101101011111010011000101001101000010 8
b10 7
1$
#1040
0$
#1060
1/
1+
b10100110100100001001001010001100101010001011111010001000100010101000011 8
b100 7
1$
#1080
0$
#1100
b1000011010010000100010101000011010010110101111101000011010011110101010101001110010101000100010101010010 8
0/
0+
b1 7
1*
b0 9
1$
#1120
0$
#1140
1"
b10001100100100101001110010010010101001101001000 8
b101 7
1$
#1160
0$
#1180
b101001101010100010000010101001001010100 8
0"
1,
b0 7
b111111111 %
b111111111 (
b111111111 <
1'
1$
#1200
0$
#1220
0,
b1000011010010000100010101000011010010110101111101000011010011110101010101001110010101000100010101010010 8
1-
b1 7
b111111111 =
0*
b1001 9
1&
0'
1$
#1240
0$
#1260
b10000110100100001000101010000110100101101011111010011000101001101000010 8
b10 7
0&
1$
#1280
0$
#1300
1.
b1001001010011100100001101011111010100100100010101000111 8
b11 7
1$
#1320
0$
#1340
b10100110100100001001001010001100101010001011111010001000100010101000011 8
0.
1/
1+
1!
b100 7
b1 #
b1 )
b1 :
b1 ;
1$
#1360
0$
#1380
0/
0+
b1000011010010000100010101000011010010110101111101000011010011110101010101001110010101000100010101010010 8
b1 7
b11111111 =
b1000 9
1$
#1400
0$
#1420
b10000110100100001000101010000110100101101011111010011000101001101000010 8
b10 7
1$
#1440
0$
#1460
1.
b1001001010011100100001101011111010100100100010101000111 8
b11 7
1$
#1480
0$
#1500
b10100110100100001001001010001100101010001011111010001000100010101000011 8
0.
1/
1+
0!
b100 7
b10 #
b10 )
b10 :
b10 ;
1$
#1520
0$
#1540
0/
0+
b1000011010010000100010101000011010010110101111101000011010011110101010101001110010101000100010101010010 8
b1 7
b1111111 =
b111 9
1$
#1560
0$
#1580
b10000110100100001000101010000110100101101011111010011000101001101000010 8
b10 7
1$
#1600
0$
#1620
1.
b1001001010011100100001101011111010100100100010101000111 8
b11 7
1$
#1640
0$
#1660
b10100110100100001001001010001100101010001011111010001000100010101000011 8
0.
1/
1+
1!
b100 7
b11 #
b11 )
b11 :
b11 ;
1$
#1680
0$
#1700
0/
0+
b1000011010010000100010101000011010010110101111101000011010011110101010101001110010101000100010101010010 8
b1 7
b111111 =
b110 9
1$
#1720
0$
#1740
b10000110100100001000101010000110100101101011111010011000101001101000010 8
b10 7
1$
#1760
0$
#1780
1.
b1001001010011100100001101011111010100100100010101000111 8
b11 7
1$
#1800
0$
#1820
b10100110100100001001001010001100101010001011111010001000100010101000011 8
0.
1/
1+
0!
b100 7
b100 #
b100 )
b100 :
b100 ;
1$
#1840
0$
#1860
0/
0+
b1000011010010000100010101000011010010110101111101000011010011110101010101001110010101000100010101010010 8
b1 7
b11111 =
b101 9
1$
#1880
0$
#1900
b10000110100100001000101010000110100101101011111010011000101001101000010 8
b10 7
1$
#1920
0$
#1940
1.
b1001001010011100100001101011111010100100100010101000111 8
b11 7
1$
#1960
0$
#1980
b10100110100100001001001010001100101010001011111010001000100010101000011 8
0.
1/
1+
1!
b100 7
b101 #
b101 )
b101 :
b101 ;
1$
#2000
0$
#2020
0/
0+
b1000011010010000100010101000011010010110101111101000011010011110101010101001110010101000100010101010010 8
b1 7
b1111 =
b100 9
1$
#2040
0$
#2060
b10000110100100001000101010000110100101101011111010011000101001101000010 8
b10 7
1$
#2080
0$
#2100
1.
b1001001010011100100001101011111010100100100010101000111 8
b11 7
1$
#2120
0$
#2140
b10100110100100001001001010001100101010001011111010001000100010101000011 8
0.
1/
1+
0!
b100 7
b110 #
b110 )
b110 :
b110 ;
1$
#2160
0$
#2180
0/
0+
b1000011010010000100010101000011010010110101111101000011010011110101010101001110010101000100010101010010 8
b1 7
b111 =
b11 9
1$
#2200
0$
#2220
b10000110100100001000101010000110100101101011111010011000101001101000010 8
b10 7
1$
#2240
0$
#2260
1.
b1001001010011100100001101011111010100100100010101000111 8
b11 7
1$
#2280
0$
#2300
b10100110100100001001001010001100101010001011111010001000100010101000011 8
0.
1/
1+
1!
b100 7
b111 #
b111 )
b111 :
b111 ;
1$
#2320
0$
#2340
0/
0+
b1000011010010000100010101000011010010110101111101000011010011110101010101001110010101000100010101010010 8
b1 7
b11 =
b10 9
1$
#2360
0$
#2380
b10000110100100001000101010000110100101101011111010011000101001101000010 8
b10 7
1$
#2400
0$
#2420
1.
b1001001010011100100001101011111010100100100010101000111 8
b11 7
1$
#2440
0$
#2460
b10100110100100001001001010001100101010001011111010001000100010101000011 8
0.
1/
1+
0!
b100 7
b1000 #
b1000 )
b1000 :
b1000 ;
1$
#2480
0$
#2500
0/
0+
b1000011010010000100010101000011010010110101111101000011010011110101010101001110010101000100010101010010 8
b1 7
b1 =
b1 9
1$
#2520
0$
#2540
b10000110100100001000101010000110100101101011111010011000101001101000010 8
b10 7
1$
#2560
0$
#2580
1.
b1001001010011100100001101011111010100100100010101000111 8
b11 7
1$
#2600
0$
#2620
b10100110100100001001001010001100101010001011111010001000100010101000011 8
0.
1/
1+
1!
b100 7
b1001 #
b1001 )
b1001 :
b1001 ;
1$
#2640
0$
#2660
0/
0+
b1000011010010000100010101000011010010110101111101000011010011110101010101001110010101000100010101010010 8
0-
b1 7
b0 =
1*
b0 9
1$
#2680
0$
#2700
b10001100100100101001110010010010101001101001000 8
1"
b101 7
1$
#2720
0$
#2740
0"
1,
b101001101010100010000010101001001010100 8
b0 7
b101010101 %
b101010101 (
b101010101 <
1'
1$
#2760
0$
#2780
b1000011010010000100010101000011010010110101111101000011010011110101010101001110010101000100010101010010 8
0,
0!
1-
b1 7
0*
b1001 9
b0 #
b0 )
b0 :
b0 ;
b101010101 =
1&
0'
1$
#2800
0$
#2820
b10000110100100001000101010000110100101101011111010011000101001101000010 8
b10 7
0&
1$
#2840
0$
#2860
b1001001010011100100001101011111010100100100010101000111 8
1.
b11 7
1$
#2880
0$
#2900
0.
1/
1+
b10100110100100001001001010001100101010001011111010001000100010101000011 8
1!
b100 7
b1 #
b1 )
b1 :
b1 ;
1$
#2920
0$
#2940
b1000011010010000100010101000011010010110101111101000011010011110101010101001110010101000100010101010010 8
0/
0+
0-
b1 7
b1000 9
b10101010 =
1$
#2960
0$
#2980
b10000110100100001000101010000110100101101011111010011000101001101000010 8
b10 7
1$
#3000
0$
#3020
b10100110100100001001001010001100101010001011111010001000100010101000011 8
1/
1+
b100 7
1$
#3040
0$
#3060
0/
0+
b1000011010010000100010101000011010010110101111101000011010011110101010101001110010101000100010101010010 8
1-
b1 7
b1010101 =
b111 9
1$
#3080
0$
#3100
b10000110100100001000101010000110100101101011111010011000101001101000010 8
b10 7
1$
#3120
0$
#3140
1.
b1001001010011100100001101011111010100100100010101000111 8
b11 7
1$
#3160
0$
#3180
b10100110100100001001001010001100101010001011111010001000100010101000011 8
0.
1/
1+
0!
b100 7
b10 #
b10 )
b10 :
b10 ;
1$
#3200
0$
#3220
0/
0+
b1000011010010000100010101000011010010110101111101000011010011110101010101001110010101000100010101010010 8
0-
b1 7
b101010 =
b110 9
1$
#3240
0$
#3260
b10000110100100001000101010000110100101101011111010011000101001101000010 8
b10 7
1$
#3280
0$
#3300
1/
1+
b10100110100100001001001010001100101010001011111010001000100010101000011 8
b100 7
1$
#3320
0$
#3340
b1000011010010000100010101000011010010110101111101000011010011110101010101001110010101000100010101010010 8
0/
0+
1-
b1 7
b101 9
b10101 =
1$
#3360
0$
#3380
b10000110100100001000101010000110100101101011111010011000101001101000010 8
b10 7
1$
#3400
0$
#3420
b1001001010011100100001101011111010100100100010101000111 8
1.
b11 7
1$
#3440
0$
#3460
0.
1/
1+
b10100110100100001001001010001100101010001011111010001000100010101000011 8
1!
b100 7
b11 #
b11 )
b11 :
b11 ;
1$
#3480
0$
#3500
b1000011010010000100010101000011010010110101111101000011010011110101010101001110010101000100010101010010 8
0/
0+
0-
b1 7
b100 9
b1010 =
1$
#3520
0$
#3540
b10000110100100001000101010000110100101101011111010011000101001101000010 8
b10 7
1$
#3560
0$
#3580
b10100110100100001001001010001100101010001011111010001000100010101000011 8
1/
1+
b100 7
1$
#3600
0$
#3620
0/
0+
b1000011010010000100010101000011010010110101111101000011010011110101010101001110010101000100010101010010 8
1-
b1 7
b101 =
b11 9
1$
#3640
0$
#3660
b10000110100100001000101010000110100101101011111010011000101001101000010 8
b10 7
1$
#3680
0$
#3700
1.
b1001001010011100100001101011111010100100100010101000111 8
b11 7
1$
#3720
0$
#3740
b10100110100100001001001010001100101010001011111010001000100010101000011 8
0.
1/
1+
0!
b100 7
b100 #
b100 )
b100 :
b100 ;
1$
#3760
0$
#3780
0/
0+
b1000011010010000100010101000011010010110101111101000011010011110101010101001110010101000100010101010010 8
0-
b1 7
b10 =
b10 9
1$
#3800
0$
#3820
b10000110100100001000101010000110100101101011111010011000101001101000010 8
b10 7
1$
#3840
0$
#3860
1/
1+
b10100110100100001001001010001100101010001011111010001000100010101000011 8
b100 7
1$
#3880
0$
#3900
b1000011010010000100010101000011010010110101111101000011010011110101010101001110010101000100010101010010 8
0/
0+
1-
b1 7
b1 9
b1 =
1$
#3920
0$
#3940
b10000110100100001000101010000110100101101011111010011000101001101000010 8
b10 7
1$
#3960
0$
#3980
b1001001010011100100001101011111010100100100010101000111 8
1.
b11 7
1$
#4000
0$
#4020
0.
1/
1+
b10100110100100001001001010001100101010001011111010001000100010101000011 8
1!
b100 7
b101 #
b101 )
b101 :
b101 ;
1$
#4040
0$
#4060
b1000011010010000100010101000011010010110101111101000011010011110101010101001110010101000100010101010010 8
0/
0+
0-
b1 7
1*
b0 9
b0 =
1$
#4080
0$
#4100
1"
b10001100100100101001110010010010101001101001000 8
b101 7
1$
#4120
0$
#4140
b101001101010100010000010101001001010100 8
0"
1,
b0 7
b111100000 %
b111100000 (
b111100000 <
1'
1$
#4160
0$
#4180
0,
b1000011010010000100010101000011010010110101111101000011010011110101010101001110010101000100010101010010 8
0!
b1 7
b111100000 =
b0 #
b0 )
b0 :
b0 ;
0*
b1001 9
1&
0'
1$
#4200
0$
#4220
b10000110100100001000101010000110100101101011111010011000101001101000010 8
b10 7
0&
1$
#4240
0$
#4260
1/
1+
b10100110100100001001001010001100101010001011111010001000100010101000011 8
b100 7
1$
#4280
0$
#4300
b1000011010010000100010101000011010010110101111101000011010011110101010101001110010101000100010101010010 8
0/
0+
b1 7
b1000 9
b11110000 =
1$
#4320
0$
#4340
b10000110100100001000101010000110100101101011111010011000101001101000010 8
b10 7
1$
#4360
0$
#4380
b10100110100100001001001010001100101010001011111010001000100010101000011 8
1/
1+
b100 7
1$
#4400
0$
#4420
0/
0+
b1000011010010000100010101000011010010110101111101000011010011110101010101001110010101000100010101010010 8
b1 7
b1111000 =
b111 9
1$
#4440
0$
#4460
b10000110100100001000101010000110100101101011111010011000101001101000010 8
b10 7
1$
#4480
0$
#4500
1/
1+
b10100110100100001001001010001100101010001011111010001000100010101000011 8
b100 7
1$
#4520
0$
#4540
b1000011010010000100010101000011010010110101111101000011010011110101010101001110010101000100010101010010 8
0/
0+
b1 7
b110 9
b111100 =
1$
#4560
0$
#4580
b10000110100100001000101010000110100101101011111010011000101001101000010 8
b10 7
1$
#4600
0$
#4620
b10100110100100001001001010001100101010001011111010001000100010101000011 8
1/
1+
b100 7
1$
#4640
0$
#4660
0/
0+
b1000011010010000100010101000011010010110101111101000011010011110101010101001110010101000100010101010010 8
b1 7
b11110 =
b101 9
1$
#4680
0$
#4700
b10000110100100001000101010000110100101101011111010011000101001101000010 8
b10 7
1$
#4720
0$
#4740
1/
1+
b10100110100100001001001010001100101010001011111010001000100010101000011 8
b100 7
1$
#4760
0$
#4780
b1000011010010000100010101000011010010110101111101000011010011110101010101001110010101000100010101010010 8
0/
0+
1-
b1 7
b100 9
b1111 =
1$
#4800
0$
#4820
b10000110100100001000101010000110100101101011111010011000101001101000010 8
b10 7
1$
#4840
0$
#4860
b1001001010011100100001101011111010100100100010101000111 8
1.
b11 7
1$
#4880
0$
#4900
0.
1/
1+
b10100110100100001001001010001100101010001011111010001000100010101000011 8
1!
b100 7
b1 #
b1 )
b1 :
b1 ;
1$
#4920
0$
#4940
b1000011010010000100010101000011010010110101111101000011010011110101010101001110010101000100010101010010 8
0/
0+
b1 7
b11 9
b111 =
1$
#4960
0$
#4980
b10000110100100001000101010000110100101101011111010011000101001101000010 8
b10 7
1$
#5000
0$
#5020
b1001001010011100100001101011111010100100100010101000111 8
1.
b11 7
1$
#5040
0$
#5060
0.
1/
1+
b10100110100100001001001010001100101010001011111010001000100010101000011 8
0!
b100 7
b10 #
b10 )
b10 :
b10 ;
1$
#5080
0$
#5100
b1000011010010000100010101000011010010110101111101000011010011110101010101001110010101000100010101010010 8
0/
0+
b1 7
b10 9
b11 =
1$
#5120
0$
#5140
b10000110100100001000101010000110100101101011111010011000101001101000010 8
b10 7
1$
#5160
0$
#5180
b1001001010011100100001101011111010100100100010101000111 8
1.
b11 7
1$
#5200
0$
#5220
0.
1/
1+
b10100110100100001001001010001100101010001011111010001000100010101000011 8
1!
b100 7
b11 #
b11 )
b11 :
b11 ;
1$
#5240
0$
#5260
b1000011010010000100010101000011010010110101111101000011010011110101010101001110010101000100010101010010 8
0/
0+
b1 7
b1 9
b1 =
1$
#5280
0$
#5300
b10000110100100001000101010000110100101101011111010011000101001101000010 8
b10 7
1$
#5320
0$
#5340
b1001001010011100100001101011111010100100100010101000111 8
1.
b11 7
1$
#5360
0$
#5380
0.
1/
1+
b10100110100100001001001010001100101010001011111010001000100010101000011 8
0!
b100 7
b100 #
b100 )
b100 :
b100 ;
1$
#5400
0$
#5420
b1000011010010000100010101000011010010110101111101000011010011110101010101001110010101000100010101010010 8
0/
0+
0-
b1 7
1*
b0 9
b0 =
1$
#5440
0$
#5460
1"
b10001100100100101001110010010010101001101001000 8
b101 7
1$
#5480
0$
#5500
b101001101010100010000010101001001010100 8
0"
1,
b0 7
b100000000 %
b100000000 (
b100000000 <
1'
1$
#5520
0$
#5540
0,
b1000011010010000100010101000011010010110101111101000011010011110101010101001110010101000100010101010010 8
b1 7
b100000000 =
b0 #
b0 )
b0 :
b0 ;
0*
b1001 9
1&
0'
1$
#5560
0$
#5580
b10000110100100001000101010000110100101101011111010011000101001101000010 8
b10 7
0&
1$
#5600
0$
#5620
1/
1+
b10100110100100001001001010001100101010001011111010001000100010101000011 8
b100 7
1$
#5640
0$
#5660
b1000011010010000100010101000011010010110101111101000011010011110101010101001110010101000100010101010010 8
0/
0+
b1 7
b1000 9
b10000000 =
1$
#5680
0$
#5700
b10000110100100001000101010000110100101101011111010011000101001101000010 8
b10 7
1$
#5720
0$
#5740
b10100110100100001001001010001100101010001011111010001000100010101000011 8
1/
1+
b100 7
1$
#5760
0$
#5780
0/
0+
b1000011010010000100010101000011010010110101111101000011010011110101010101001110010101000100010101010010 8
b1 7
b1000000 =
b111 9
1$
#5800
0$
#5820
b10000110100100001000101010000110100101101011111010011000101001101000010 8
b10 7
1$
#5840
0$
#5860
1/
1+
b10100110100100001001001010001100101010001011111010001000100010101000011 8
b100 7
1$
#5880
0$
#5900
b1000011010010000100010101000011010010110101111101000011010011110101010101001110010101000100010101010010 8
0/
0+
b1 7
b110 9
b100000 =
1$
#5920
0$
#5940
b10000110100100001000101010000110100101101011111010011000101001101000010 8
b10 7
1$
#5960
0$
#5980
b10100110100100001001001010001100101010001011111010001000100010101000011 8
1/
1+
b100 7
1$
#6000
0$
#6020
0/
0+
b1000011010010000100010101000011010010110101111101000011010011110101010101001110010101000100010101010010 8
b1 7
b10000 =
b101 9
1$
#6040
0$
#6060
b10000110100100001000101010000110100101101011111010011000101001101000010 8
b10 7
1$
#6080
0$
#6100
1/
1+
b10100110100100001001001010001100101010001011111010001000100010101000011 8
b100 7
1$
#6120
0$
#6140
b1000011010010000100010101000011010010110101111101000011010011110101010101001110010101000100010101010010 8
0/
0+
b1 7
b100 9
b1000 =
1$
#6160
0$
#6180
b10000110100100001000101010000110100101101011111010011000101001101000010 8
b10 7
1$
#6200
0$
#6220
b10100110100100001001001010001100101010001011111010001000100010101000011 8
1/
1+
b100 7
1$
#6240
0$
#6260
0/
0+
b1000011010010000100010101000011010010110101111101000011010011110101010101001110010101000100010101010010 8
b1 7
b100 =
b11 9
1$
#6280
0$
#6300
b10000110100100001000101010000110100101101011111010011000101001101000010 8
b10 7
1$
#6320
0$
#6340
1/
1+
b10100110100100001001001010001100101010001011111010001000100010101000011 8
b100 7
1$
#6360
0$
#6380
b1000011010010000100010101000011010010110101111101000011010011110101010101001110010101000100010101010010 8
0/
0+
b1 7
b10 9
b10 =
1$
#6400
0$
#6420
b10000110100100001000101010000110100101101011111010011000101001101000010 8
b10 7
1$
#6440
0$
#6460
b10100110100100001001001010001100101010001011111010001000100010101000011 8
1/
1+
b100 7
1$
#6480
0$
#6500
0/
0+
b1000011010010000100010101000011010010110101111101000011010011110101010101001110010101000100010101010010 8
1-
b1 7
b1 =
b1 9
1$
#6520
0$
#6540
b10000110100100001000101010000110100101101011111010011000101001101000010 8
b10 7
1$
#6560
0$
#6580
1.
b1001001010011100100001101011111010100100100010101000111 8
b11 7
1$
#6600
0$
#6620
b10100110100100001001001010001100101010001011111010001000100010101000011 8
0.
1/
1+
1!
b100 7
b1 #
b1 )
b1 :
b1 ;
1$
#6640
0$
#6660
0/
0+
b1000011010010000100010101000011010010110101111101000011010011110101010101001110010101000100010101010010 8
0-
b1 7
b0 =
1*
b0 9
1$
#6680
0$
#6700
b10001100100100101001110010010010101001101001000 8
1"
b101 7
1$
#6720
0$
#6740
b1 6
1$
