Entrega_Final/multiplicador/ACCR.v
module ACCR (clk, A, ADD, reset, R);

//señales de control
input clk;
input ADD;
input reset;

// entradas y salidas
input [31:0]A;
output reg [31:0] R;

always @(negedge clk) 
begin
    if (reset)
        R <= 32'b0;
    else if(ADD)
        R <= R+A;
    
end
    
endmodule

Entrega_Final/multiplicador/ACCR_TB.v
module ACCR_TB;
reg clk;
reg ADD;
reg reset;
reg [31:0]A;
wire [31:0] R;

ACCR uut(.clk(clk), .A(A), .ADD(ADD), .reset(reset), .R(R));

initial begin
    clk = 0;
    forever #20clk=~clk;
end
initial begin
    $dumpfile("ACCR_TB.vcd");
    $dumpvars(0, ACCR_TB);

    reset=1;
    ADD=0;
    A=32'd10;
    @(negedge clk);
    reset=0;
    @(negedge clk);
    ADD=1;
    @(negedge clk);
    ADD=0;
    #40;
    A=32'd115;
    @(negedge clk);
    ADD=1;
    @(negedge clk);
    ADD=0;
    @(negedge clk);
    reset=1;
    @(negedge clk);
    reset=0;
    #40;
    A=32'b11111111111111111111111111111111;
    ADD=1;
    #20;
    ADD=0;
    #40;
    ADD=1;
    #40;
    ADD=0;
    #80;
    $finish;

end
endmodule

Entrega_Final/multiplicador/ACCR_TB.vcd
$date
	Mon Jul 13 19:09:19 2026
$end
$version
	Icarus Verilog
$end
$timescale
	1s
$end
$scope module ACCR_TB $end
$var wire 32 ! R [31:0] $end
$var reg 32 " A [31:0] $end
$var reg 1 # ADD $end
$var reg 1 $ clk $end
$var reg 1 % reset $end
$scope module uut $end
$var wire 32 & A [31:0] $end
$var wire 1 # ADD $end
$var wire 1 $ clk $end
$var wire 1 % reset $end
$var reg 32 ' R [31:0] $end
$upscope $end
$upscope $end
$enddefinitions $end
$comment Show the parameter values. $end
$dumpall
$end
#0
$dumpvars
b0 '
b1010 &
1%
0$
0#
b1010 "
b0 !
$end
#20
1$
#40
0%
0$
#60
1$
#80
b1010 !
b1010 '
1#
0$
#100
1$
#120
b10100 !
b10100 '
0#
0$
#140
1$
#160
b10000111 !
b10000111 '
1#
0$
b1110011 "
b1110011 &
#180
1$
#200
b11111010 !
b11111010 '
0#
0$
#220
1$
#240
b0 !
b0 '
1%
0$
#260
1$
#280
0%
0$
#300
1$
#320
b11111111111111111111111111111111 !
b11111111111111111111111111111111 '
0$
1#
b11111111111111111111111111111111 "
b11111111111111111111111111111111 &
#340
1$
0#
#360
0$
#380
1$
1#
#400
b11111111111111111111111111111110 !
b11111111111111111111111111111110 '
0$
#420
1$
0#
