Entrega_Final/multiplicador/control.v
module control (clk, rst, init, LSB, Zero, ADD, load, Shft_Dec, done);
input clk;
input rst;
input init;
input LSB;
input Zero;
output reg ADD;
output reg load;
output reg Shft_Dec;
output reg done;

//estados

parameter  Start = 3'b000;
parameter  Check_Counter = 3'b001;
parameter  Check_LSB = 3'b010;
parameter  Add = 3'b011;
parameter  Shift = 3'b100;
parameter  Show_Result = 3'b101;

reg [2:0] STATE;
reg [4:0] count;


always @(posedge clk or posedge rst) 
begin
    if (rst)begin
        STATE <= Start;
    end
    else 
    begin
    case(STATE)
        Start:
        begin
            count<=0;
            if(init)
                STATE = Check_Counter;
            else 
                STATE = Start;
        end
        Check_Counter:
        begin
            if(Zero)
                STATE=Show_Result;
            else
                STATE=Check_LSB;
        end
        Check_LSB:
        begin
            if(LSB)
                STATE=Add;
            else
                STATE=Shift; 
        end
        Add:
        begin
            STATE=Shift;
        end
        Shift:
        begin
            STATE=Check_Counter;
        end
        Show_Result:
        begin
           count <= count + 1;
            if (count >= 28)
                STATE=Start;
            else 
                STATE = Show_Result;
        end
        default:
            STATE=Start; 
    endcase
    end
end
always @(*) 
begin
   case (STATE)
    Start:
    begin
        load=1;
        ADD=0;
        Shft_Dec=0;
        done=0;
    end
    Check_Counter:
    begin
        done=0;
        load=0;
        ADD=0;
        Shft_Dec=0;
    end
    Check_LSB:
    begin
        done=0;
        load=0;
        ADD=0;
        Shft_Dec=0;
    end
    Add:
    begin
        ADD=1;
        load=0;
        Shft_Dec=0;
        done=0;
    end
    Shift:
    begin
        Shft_Dec=1;
        load=0;
        ADD=0;
        done=0;
    end
    Show_Result:
    begin
        done=1;
        load=0;
        ADD=0;
        Shft_Dec=0;
    end

    default:
    begin
        done=0;
        load=0;
        ADD=0;
        Shft_Dec=0;
    end


   endcase 
end
    
endmodule

Entrega_Final/multiplicador/comp.v
module comp (Out_C, Zero);
//entradas y salidas
input [4:0] Out_C;
output Zero;
//comparación
assign Zero = (Out_C==0);
endmodule

Entrega_Final/multiplicador/Counter.v
module Counter (clk, load, Shft_Dec, Out_C);

//señales de control
input clk;
input load;
input Shft_Dec;

//salida
output reg [4:0]Out_C; // como el número es de máximo 16 bits por ahora entonces el contador solo necesita 5 bits

always @(negedge clk) 
begin
    if (load)
        Out_C <= 5'd16; 
    else if(Shft_Dec)
        Out_C <= Out_C - 1;
        
end
    
endmodule

Entrega_Final/multiplicador/ACCR.v
module ACCR (clk, A, ADD, reset, R);

//señales de control
input clk;
input ADD;
input reset;

// entradas y salidas
input [31:0]A;
output reg [31:0] R;

always @(negedge clk) 
begin
    if (reset)
        R <= 32'b0;
    else if(ADD)
        R <= R+A;
    
end
    
endmodule

Entrega_Final/multiplicador/RCI.v
//MODULO REGISTRO DE CORRIMIENTO A LA IZQUIERDA
module RCI (clk, load, in_A, Shft_Dec, Out_A);

// señales de control
input clk;
input Shft_Dec;
input load;

// entradas y salidas
input [15:0] in_A;
output reg [31:0] Out_A;

always @(negedge clk)
begin

    if(load)
        Out_A <= in_A;

    else if(Shft_Dec)
        Out_A <= Out_A << 1;

end
endmodule

Entrega_Final/multiplicador/RCD.v
//REGISTRO DE CORRIMIENTO A LA DERECHA
module RCD (clk, in_B, load, Shft_Dec, Out_B);

//señales de control
input clk;
input load;
input Shft_Dec;

//entradas y salidas
input [15:0]in_B;
output reg[15:0]Out_B;

always @(negedge clk) 
begin
    if (load)
        Out_B <= in_B;

    else if(Shft_Dec)
        Out_B <= Out_B >> 1;
        
end
endmodule

Entrega_Final/multiplicador/multiplicador.v
module multiplicador (clk, rst, init, A, B, R, done);
//señales externas
input clk;
input rst;
input init;
output done;

//entradas y salidas
input [15:0]A;
input [15:0]B;
output [31:0]R;

//señales internas
wire Shft_Dec;
wire ADD;
wire load;
wire w_Zero;
wire [31:0] w_A;
wire [15:0] w_B;
wire [4:0] w_C;

//implementacion de modulos
RCD RCD0(.clk(clk), .in_B(B), .load(load), .Shft_Dec(Shft_Dec), .Out_B(w_B));
RCI RCI0(.clk(clk), .load(load), .in_A(A), .Shft_Dec(Shft_Dec), .Out_A(w_A));
ACCR ACCR0(.clk(clk), .A(w_A), .ADD(ADD), .reset(load), .R(R));
Counter Counter0(.clk(clk), .load(load), .Shft_Dec(Shft_Dec), .Out_C(w_C));
comp comp0(.Out_C(w_C), .Zero(w_Zero));
control control0(.clk(clk), .rst(rst), .init(init), .LSB(w_B[0]), .Zero(w_Zero), .ADD(ADD), .load(load), .Shft_Dec(Shft_Dec), .done(done));

endmodule

Entrega_Final/multiplicador/multiplicador_TB.v
module multiplicador_TB;
reg clk;
reg rst;
reg init;
wire done;
reg [15:0]A;
reg [15:0]B;
wire [31:0]R;

multiplicador uut(.clk(clk), .rst(rst), .init(init), .A(A), .B(B), .R(R), .done(done));
initial begin
    clk=0;
    forever #20 clk=~clk;
end
initial begin
    $dumpfile("multiplicador_TB.vcd");
    $dumpvars(0, multiplicador_TB);
    
    init=0;
    rst=1;
    A=100;
    B=10;
    @(posedge clk);
    rst=0;
    @(posedge clk);
    init=1;
    @(posedge clk);
    init=0;
    wait(done);
    #40;
    rst=1;
    A=240;
    B=130;
    @(posedge clk);
    rst=0;
    @(posedge clk);
    init=1;
    @(posedge clk);
    init=0;
    wait(done);
    #40;
    rst=1;
    A=789;
    B=51;
    @(posedge clk);
    rst=0;
    @(posedge clk);
    init=1;
    @(posedge clk);
    init=0;
    wait(done);
    #40;
    $finish;


end

endmodule

Entrega_Final/multiplicador/multiplicador_TB.vcd
$date
	Thu Jul 16 10:53:39 2026
$end
$version
	Icarus Verilog
$end
$timescale
	1s
$end
$scope module multiplicador_TB $end
$var wire 1 ! done $end
$var wire 32 " R [31:0] $end
$var reg 16 # A [15:0] $end
$var reg 16 $ B [15:0] $end
$var reg 1 % clk $end
$var reg 1 & init $end
$var reg 1 ' rst $end
$scope module uut $end
$var wire 16 ( A [15:0] $end
$var wire 16 ) B [15:0] $end
$var wire 1 % clk $end
$var wire 1 & init $end
$var wire 1 ' rst $end
$var wire 1 * w_Zero $end
$var wire 5 + w_C [4:0] $end
$var wire 16 , w_B [15:0] $end
$var wire 32 - w_A [31:0] $end
$var wire 1 . load $end
$var wire 1 ! done $end
$var wire 1 / Shft_Dec $end
$var wire 32 0 R [31:0] $end
$var wire 1 1 ADD $end
$scope module ACCR0 $end
$var wire 1 % clk $end
$var wire 1 . reset $end
$var wire 1 1 ADD $end
$var wire 32 2 A [31:0] $end
$var reg 32 3 R [31:0] $end
$upscope $end
$scope module Counter0 $end
$var wire 1 % clk $end
$var wire 1 . load $end
$var wire 1 / Shft_Dec $end
$var reg 5 4 Out_C [4:0] $end
$upscope $end
$scope module RCD0 $end
$var wire 1 % clk $end
$var wire 16 5 in_B [15:0] $end
$var wire 1 . load $end
$var wire 1 / Shft_Dec $end
$var reg 16 6 Out_B [15:0] $end
$upscope $end
$scope module RCI0 $end
$var wire 1 % clk $end
$var wire 16 7 in_A [15:0] $end
$var wire 1 . load $end
$var wire 1 / Shft_Dec $end
$var reg 32 8 Out_A [31:0] $end
$upscope $end
$scope module comp0 $end
$var wire 5 9 Out_C [4:0] $end
$var wire 1 * Zero $end
$upscope $end
$scope module control0 $end
$var wire 1 : LSB $end
$var wire 1 * Zero $end
$var wire 1 % clk $end
$var wire 1 & init $end
$var wire 1 ' rst $end
$var parameter 3 ; Add $end
$var parameter 3 < Check_Counter $end
$var parameter 3 = Check_LSB $end
$var parameter 3 > Shift $end
$var parameter 3 ? Show_Result $end
$var parameter 3 @ Start $end
$var reg 1 1 ADD $end
$var reg 3 A STATE [2:0] $end
$var reg 1 / Shft_Dec $end
$var reg 5 B count [4:0] $end
$var reg 1 ! done $end
$var reg 1 . load $end
$upscope $end
$upscope $end
$upscope $end
$enddefinitions $end
$comment Show the parameter values. $end
$dumpall
b0 @
b101 ?
b100 >
b10 =
b1 <
b11 ;
$end
#0
$dumpvars
bx B
b0 A
x:
bx 9
bx 8
b1100100 7
bx 6
b1010 5
bx 4
bx 3
bx 2
01
bx 0
0/
1.
bx -
bx ,
bx +
x*
b1010 )
b1100100 (
1'
0&
0%
b1010 $
b1100100 #
bx "
0!
$end
#20
b0 B
0'
1%
#40
0:
0*
b10000 +
b10000 4
b10000 9
b0 "
b0 0
b0 3
b1100100 -
b1100100 2
b1100100 8
b1010 ,
b1010 6
0%
#60
0.
b1 A
1&
1%
#80
0%
#100
b10 A
0&
1%
#120
0%
#140
1/
b100 A
1%
#160
1:
b101 ,
b101 6
b11001000 -
b11001000 2
b11001000 8
b1111 +
b1111 4
b1111 9
0%
#180
0/
b1 A
1%
#200
0%
#220
b10 A
1%
#240
0%
#260
11
b11 A
1%
#280
b11001000 "
b11001000 0
b11001000 3
0%
#300
01
1/
b100 A
1%
#320
0:
b10 ,
b10 6
b110010000 -
b110010000 2
b110010000 8
b1110 +
b1110 4
b1110 9
0%
#340
0/
b1 A
1%
#360
0%
#380
b10 A
1%
#400
0%
#420
1/
b100 A
1%
#440
1:
b1101 +
b1101 4
b1101 9
b1100100000 -
b1100100000 2
b1100100000 8
b1 ,
b1 6
0%
#460
0/
b1 A
1%
#480
0%
#500
b10 A
1%
#520
0%
#540
11
b11 A
1%
#560
b1111101000 "
b1111101000 0
b1111101000 3
0%
#580
01
1/
b100 A
1%
#600
0:
b1100 +
b1100 4
b1100 9
b11001000000 -
b11001000000 2
b11001000000 8
b0 ,
b0 6
0%
#620
0/
b1 A
1%
#640
0%
#660
b10 A
1%
#680
0%
#700
1/
b100 A
1%
#720
b110010000000 -
b110010000000 2
b110010000000 8
b1011 +
b1011 4
b1011 9
0%
#740
0/
b1 A
1%
#760
0%
#780
b10 A
1%
#800
0%
#820
1/
b100 A
1%
#840
b1010 +
b1010 4
b1010 9
b1100100000000 -
b1100100000000 2
b1100100000000 8
0%
#860
0/
b1 A
1%
#880
0%
#900
b10 A
1%
#920
0%
#940
1/
b100 A
1%
#960
b11001000000000 -
b11001000000000 2
b11001000000000 8
b1001 +
b1001 4
b1001 9
0%
#980
0/
b1 A
1%
#1000
0%
#1020
b10 A
1%
#1040
0%
#1060
1/
b100 A
1%
#1080
b1000 +
b1000 4
b1000 9
b110010000000000 -
b110010000000000 2
b110010000000000 8
0%
#1100
0/
b1 A
1%
#1120
0%
#1140
b10 A
1%
#1160
0%
#1180
1/
b100 A
1%
#1200
b1100100000000000 -
b1100100000000000 2
b1100100000000000 8
b111 +
b111 4
b111 9
0%
#1220
0/
b1 A
1%
#1240
0%
#1260
b10 A
1%
#1280
0%
#1300
1/
b100 A
1%
#1320
b110 +
b110 4
b110 9
b11001000000000000 -
b11001000000000000 2
b11001000000000000 8
0%
#1340
0/
b1 A
1%
#1360
0%
#1380
b10 A
1%
#1400
0%
#1420
1/
b100 A
1%
#1440
b110010000000000000 -
b110010000000000000 2
b110010000000000000 8
b101 +
b101 4
b101 9
0%
#1460
0/
b1 A
1%
#1480
0%
#1500
b10 A
1%
#1520
0%
#1540
1/
b100 A
1%
#1560
b100 +
b100 4
b100 9
b1100100000000000000 -
b1100100000000000000 2
b1100100000000000000 8
0%
#1580
0/
b1 A
1%
#1600
0%
#1620
b10 A
1%
#1640
0%
#1660
1/
b100 A
1%
#1680
b11001000000000000000 -
b11001000000000000000 2
b11001000000000000000 8
b11 +
b11 4
b11 9
0%
#1700
0/
b1 A
1%
#1720
0%
#1740
b10 A
1%
#1760
0%
#1780
1/
b100 A
1%
#1800
b10 +
b10 4
b10 9
b110010000000000000000 -
b110010000000000000000 2
b110010000000000000000 8
0%
#1820
0/
b1 A
1%
#1840
0%
#1860
b10 A
1%
#1880
0%
#1900
1/
b100 A
1%
#1920
b1100100000000000000000 -
b1100100000000000000000 2
b1100100000000000000000 8
b1 +
b1 4
b1 9
0%
#1940
0/
b1 A
1%
#1960
0%
#1980
b10 A
1%
#2000
0%
#2020
1/
b100 A
1%
#2040
1*
b0 +
b0 4
b0 9
b11001000000000000000000 -
b11001000000000000000000 2
b11001000000000000000000 8
0%
#2060
0/
b1 A
1%
#2080
0%
#2100
1!
b101 A
1%
#2120
0%
#2140
0!
1.
b0 A
1%
b10000010 $
b10000010 )
b10000010 5
b11110000 #
b11110000 (
b11110000 7
0'
#2160
b10000010 ,
b10000010 6
b11110000 -
b11110000 2
b11110000 8
b0 "
b0 0
b0 3
0*
b10000 +
b10000 4
b10000 9
0%
#2180
0.
b1 A
1&
1%
#2200
0%
#2220
b10 A
0&
1%
#2240
0%
#2260
1/
b100 A
1%
#2280
1:
b1111 +
b1111 4
b1111 9
b111100000 -
b111100000 2
b111100000 8
b1000001 ,
b1000001 6
0%
#2300
0/
b1 A
1%
#2320
0%
#2340
b10 A
1%
#2360
0%
#2380
11
b11 A
1%
#2400
b111100000 "
b111100000 0
b111100000 3
0%
#2420
01
1/
b100 A
1%
#2440
0:
b1110 +
b1110 4
b1110 9
b1111000000 -
b1111000000 2
b1111000000 8
b100000 ,
b100000 6
0%
#2460
0/
b1 A
1%
#2480
0%
#2500
b10 A
1%
#2520
0%
#2540
1/
b100 A
1%
#2560
b10000 ,
b10000 6
b11110000000 -
b11110000000 2
b11110000000 8
b1101 +
b1101 4
b1101 9
0%
#2580
0/
b1 A
1%
#2600
0%
#2620
b10 A
1%
#2640
0%
#2660
1/
b100 A
1%
#2680
b1100 +
b1100 4
b1100 9
b111100000000 -
b111100000000 2
b111100000000 8
b1000 ,
b1000 6
0%
#2700
0/
b1 A
1%
#2720
0%
#2740
b10 A
1%
#2760
0%
#2780
1/
b100 A
1%
#2800
b100 ,
b100 6
b1111000000000 -
b1111000000000 2
b1111000000000 8
b1011 +
b1011 4
b1011 9
0%
#2820
0/
b1 A
1%
#2840
0%
#2860
b10 A
1%
#2880
0%
#2900
1/
b100 A
1%
#2920
b1010 +
b1010 4
b1010 9
b11110000000000 -
b11110000000000 2
b11110000000000 8
b10 ,
b10 6
0%
#2940
0/
b1 A
1%
#2960
0%
#2980
b10 A
1%
#3000
0%
#3020
1/
b100 A
1%
#3040
1:
b1 ,
b1 6
b111100000000000 -
b111100000000000 2
b111100000000000 8
b1001 +
b1001 4
b1001 9
0%
#3060
0/
b1 A
1%
#3080
0%
#3100
b10 A
1%
#3120
0%
#3140
11
b11 A
1%
#3160
b111100111100000 "
b111100111100000 0
b111100111100000 3
0%
#3180
01
1/
b100 A
1%
#3200
0:
b0 ,
b0 6
b1111000000000000 -
b1111000000000000 2
b1111000000000000 8
b1000 +
b1000 4
b1000 9
0%
#3220
0/
b1 A
1%
#3240
0%
#3260
b10 A
1%
#3280
0%
#3300
1/
b100 A
1%
#3320
b111 +
b111 4
b111 9
b11110000000000000 -
b11110000000000000 2
b11110000000000000 8
0%
#3340
0/
b1 A
1%
#3360
0%
#3380
b10 A
1%
#3400
0%
#3420
1/
b100 A
1%
#3440
b111100000000000000 -
b111100000000000000 2
b111100000000000000 8
b110 +
b110 4
b110 9
0%
#3460
0/
b1 A
1%
#3480
0%
#3500
b10 A
1%
#3520
0%
#3540
1/
b100 A
1%
#3560
b101 +
b101 4
b101 9
b1111000000000000000 -
b1111000000000000000 2
b1111000000000000000 8
0%
#3580
0/
b1 A
1%
#3600
0%
#3620
b10 A
1%
#3640
0%
#3660
1/
b100 A
1%
#3680
b11110000000000000000 -
b11110000000000000000 2
b11110000000000000000 8
b100 +
b100 4
b100 9
0%
#3700
0/
b1 A
1%
#3720
0%
#3740
b10 A
1%
#3760
0%
#3780
1/
b100 A
1%
#3800
b11 +
b11 4
b11 9
b111100000000000000000 -
b111100000000000000000 2
b111100000000000000000 8
0%
#3820
0/
b1 A
1%
#3840
0%
#3860
b10 A
1%
#3880
0%
#3900
1/
b100 A
1%
#3920
b1111000000000000000000 -
b1111000000000000000000 2
b1111000000000000000000 8
b10 +
b10 4
b10 9
0%
#3940
0/
b1 A
1%
#3960
0%
#3980
b10 A
1%
#4000
0%
#4020
1/
b100 A
1%
#4040
b1 +
b1 4
b1 9
b11110000000000000000000 -
b11110000000000000000000 2
b11110000000000000000000 8
0%
#4060
0/
b1 A
1%
#4080
0%
#4100
b10 A
1%
#4120
0%
#4140
1/
b100 A
1%
#4160
b111100000000000000000000 -
b111100000000000000000000 2
b111100000000000000000000 8
1*
b0 +
b0 4
b0 9
0%
#4180
0/
b1 A
1%
#4200
0%
#4220
1!
b101 A
1%
#4240
0%
#4260
0!
1.
b0 A
1%
b110011 $
b110011 )
b110011 5
b1100010101 #
b1100010101 (
b1100010101 7
0'
#4280
1:
0*
b10000 +
b10000 4
b10000 9
b0 "
b0 0
b0 3
b1100010101 -
b1100010101 2
b1100010101 8
b110011 ,
b110011 6
0%
#4300
0.
b1 A
1&
1%
#4320
0%
#4340
b10 A
0&
1%
#4360
0%
#4380
11
b11 A
1%
#4400
b1100010101 "
b1100010101 0
b1100010101 3
0%
#4420
01
1/
b100 A
1%
#4440
b1111 +
b1111 4
b1111 9
b11000101010 -
b11000101010 2
b11000101010 8
b11001 ,
b11001 6
0%
#4460
0/
b1 A
1%
#4480
0%
#4500
b10 A
1%
#4520
0%
#4540
11
b11 A
1%
#4560
b100100111111 "
b100100111111 0
b100100111111 3
0%
#4580
01
1/
b100 A
1%
#4600
0:
b1110 +
b1110 4
b1110 9
b110001010100 -
b110001010100 2
b110001010100 8
b1100 ,
b1100 6
0%
#4620
0/
b1 A
1%
#4640
0%
#4660
b10 A
1%
#4680
0%
#4700
1/
b100 A
1%
#4720
b110 ,
b110 6
b1100010101000 -
b1100010101000 2
b1100010101000 8
b1101 +
b1101 4
b1101 9
0%
#4740
0/
b1 A
1%
#4760
0%
#4780
b10 A
1%
#4800
0%
#4820
1/
b100 A
1%
#4840
1:
b1100 +
b1100 4
b1100 9
b11000101010000 -
b11000101010000 2
b11000101010000 8
b11 ,
b11 6
0%
#4860
0/
b1 A
1%
#4880
0%
#4900
b10 A
1%
#4920
0%
#4940
11
b11 A
1%
#4960
b11101010001111 "
b11101010001111 0
b11101010001111 3
0%
#4980
01
1/
b100 A
1%
#5000
b1011 +
b1011 4
b1011 9
b110001010100000 -
b110001010100000 2
b110001010100000 8
b1 ,
b1 6
0%
#5020
0/
b1 A
1%
#5040
0%
#5060
b10 A
1%
#5080
0%
#5100
11
b11 A
1%
#5120
b1001110100101111 "
b1001110100101111 0
b1001110100101111 3
0%
#5140
01
1/
b100 A
1%
#5160
0:
b1010 +
b1010 4
b1010 9
b1100010101000000 -
b1100010101000000 2
b1100010101000000 8
b0 ,
b0 6
0%
#5180
0/
b1 A
1%
#5200
0%
#5220
b10 A
1%
#5240
0%
#5260
1/
b100 A
1%
#5280
b11000101010000000 -
b11000101010000000 2
b11000101010000000 8
b1001 +
b1001 4
b1001 9
0%
#5300
0/
b1 A
1%
#5320
0%
#5340
b10 A
1%
#5360
0%
#5380
1/
b100 A
1%
#5400
b1000 +
b1000 4
b1000 9
b110001010100000000 -
b110001010100000000 2
b110001010100000000 8
0%
#5420
0/
b1 A
1%
#5440
0%
#5460
b10 A
1%
#5480
0%
#5500
1/
b100 A
1%
#5520
b1100010101000000000 -
b1100010101000000000 2
b1100010101000000000 8
b111 +
b111 4
b111 9
0%
#5540
0/
b1 A
1%
#5560
0%
#5580
b10 A
1%
#5600
0%
#5620
1/
b100 A
1%
#5640
b110 +
b110 4
b110 9
b11000101010000000000 -
b11000101010000000000 2
b11000101010000000000 8
0%
#5660
0/
b1 A
1%
#5680
0%
#5700
b10 A
1%
#5720
0%
#5740
1/
b100 A
1%
#5760
b110001010100000000000 -
b110001010100000000000 2
b110001010100000000000 8
b101 +
b101 4
b101 9
0%
#5780
0/
b1 A
1%
#5800
0%
#5820
b10 A
1%
#5840
0%
#5860
1/
b100 A
1%
#5880
b100 +
b100 4
b100 9
b1100010101000000000000 -
b1100010101000000000000 2
b1100010101000000000000 8
0%
#5900
0/
b1 A
1%
#5920
0%
#5940
b10 A
1%
#5960
0%
#5980
1/
b100 A
1%
#6000
b11000101010000000000000 -
b11000101010000000000000 2
b11000101010000000000000 8
b11 +
b11 4
b11 9
0%
#6020
0/
b1 A
1%
#6040
0%
#6060
b10 A
1%
#6080
0%
#6100
1/
b100 A
1%
#6120
b10 +
b10 4
b10 9
b110001010100000000000000 -
b110001010100000000000000 2
b110001010100000000000000 8
0%
#6140
0/
b1 A
1%
#6160
0%
#6180
b10 A
1%
#6200
0%
#6220
1/
b100 A
1%
#6240
b1100010101000000000000000 -
b1100010101000000000000000 2
b1100010101000000000000000 8
b1 +
b1 4
b1 9
0%
#6260
0/
b1 A
1%
#6280
0%
#6300
b10 A
1%
#6320
0%
#6340
1/
b100 A
1%
#6360
1*
b0 +
b0 4
b0 9
b11000101010000000000000000 -
b11000101010000000000000000 2
b11000101010000000000000000 8
0%
#6380
0/
b1 A
1%
#6400
0%
#6420
1!
b101 A
1%
#6440
0%
#6460
b1 B
1%
