Entrega_Final/bin_bcd/control.v
module control (clk, rst, init, Zero, Load, SHFT, add, DEC, done);
input clk;
input rst;
input init;
input Zero;
output reg Load;
output reg SHFT;
output reg add;
output reg DEC;
output reg done;

parameter START = 3'b000;
parameter SHIFT_DEC = 3'b001;
parameter CHECK_COUNTER = 3'b010;
parameter ENABLE_SUM = 3'b011;
parameter FINISH = 3'b100;
reg [2:0] STATE;
reg [5:0] counts;

always @(posedge clk or posedge rst) 
begin
    if (rst) 
    begin
        STATE <= START;    
    end
    else begin
        case (STATE)
            START:
            begin
                counts <= 0;
                if (init) 
                begin
                    STATE <= SHIFT_DEC;    
                end
                else
                    STATE <= START;
            end
            SHIFT_DEC:
            begin
                STATE <= CHECK_COUNTER;
            end
            CHECK_COUNTER:
            begin
                if (Zero) 
                begin
                    STATE <= FINISH;    
                end
                else
                    STATE <= ENABLE_SUM;
            end
            ENABLE_SUM:
            begin
                STATE <= SHIFT_DEC;
            end
            FINISH:
            begin
                counts <= counts + 1;
                if (counts >= 28) 
                begin
                    STATE <= START;    
                end
                else
                    STATE <= FINISH;

            end
            default:
                STATE <= START;
        endcase
    end
end
always @(*) 
begin
    case (STATE)
        START:
        begin
            Load = 1;
            SHFT = 0;
            add = 0;
            DEC = 0;
            done = 0; 
        end
        SHIFT_DEC:
        begin
            Load = 0;
            SHFT = 1;
            add = 0;
            DEC = 1;
            done = 0; 
        end
        CHECK_COUNTER:
        begin
            Load = 0;
            SHFT = 0;
            add = 0;
            DEC = 0;
            done = 0;       
        end
        ENABLE_SUM:
        begin
            Load = 0;
            SHFT = 0;
            add = 1;
            DEC = 0;
            done = 0;    
        end
        FINISH:
        begin
            Load = 0;
            SHFT = 0;
            add = 0;
            DEC = 0;
            done = 1;              
        end
        default:
        begin
            Load = 0;
            SHFT = 0;
            add = 0;
            DEC = 0;
            done = 0;     
        end
    endcase
    
end
`ifdef BENCH
reg [8*20:1] estados;
always @(*) begin
    case (STATE)
        START: estados="START";
        SHIFT_DEC: estados="SHIFT_DEC";
        CHECK_COUNTER: estados="CHECK_COUNTER";
        ENABLE_SUM: estados="ENABLE_SUM";
        FINISH: estados="FINISH";
        default: estados="unknown";
    endcase
end
`endif
endmodule

Entrega_Final/bin_bcd/counter.v
module counter (clk, DEC, Load, Zero);
    input clk;
    input DEC;
    input Load;
    output Zero;
    reg[4:0] count;
    assign Zero = (count==0);
always @(posedge clk) 
begin
    if (Load)
    begin
        count <= 5'd16;
    end
    else if (DEC) 
    begin
        count <= count - 1;
    end
end
endmodule

Entrega_Final/bin_bcd/sum.v
module sum (in_nibble, out_nibble);
    input [3:0] in_nibble;
    output [3:0] out_nibble;
    assign out_nibble = in_nibble + 4'd3;    
endmodule

Entrega_Final/bin_bcd/comp.v
module comp (in_comp, update);
input [3:0]in_comp;
output update;
assign update = (in_comp >= 4'd5);
endmodule

Entrega_Final/bin_bcd/comblsr.v
module comblsr(clk, update, SHFT, add, Load, in_Bin, in_bcd, BCD_Out);
    // señales de control
    input clk;
    input SHFT;
    input add;
    input Load;
    input [4:0] update;

    //entradas
    input [15:0] in_Bin;
    input [19:0] in_bcd;
    //salida
    output [19:0] BCD_Out;
    reg[35:0] alldata;
    assign BCD_Out=alldata[35:16];



always @(posedge clk) begin
    if (Load) 
    begin
        alldata[35:16] <= 20'b0; 
        alldata[15:0] <= in_Bin;
    end
    else if (SHFT) begin
        alldata <= alldata << 1;
    end
    else if (add) 
    begin
        if(update[4]==1'b1)
            alldata[35:32]<=in_bcd[19:16];
        if(update[3]==1'b1)
            alldata[31:28]<=in_bcd[15:12];
        if(update[2]==1'b1)
            alldata[27:24]<=in_bcd[11:8];
        if(update[1]==1'b1)
            alldata[23:20]<=in_bcd[7:4];
        if(update[0]==1'b1)
            alldata[19:16]<=in_bcd[3:0];
    end

end



endmodule

Entrega_Final/bin_bcd/bin2bcd.v
module bin2bcd (clk, rst, init, Bin, BCD, done);

input clk;
input rst;
input init;
input [15:0] Bin;
output [19:0] BCD;
output done;

wire Load;
wire SHFT;
wire add;
wire DEC;
wire Zero;
wire [19:0] bcd_reg;
wire [19:0] bcd_add;
wire [4:0] update;

comblsr REG0(.clk(clk), .update(update), .SHFT(SHFT), .add(add), .Load(Load), .in_Bin(Bin), .in_bcd(bcd_add), .BCD_Out(bcd_reg));
comp comp0(.in_comp(bcd_reg[3:0]), .update(update[0]));
comp comp1(.in_comp(bcd_reg[7:4]), .update(update[1]));
comp comp2(.in_comp(bcd_reg[11:8]), .update(update[2]));
comp comp3(.in_comp(bcd_reg[15:12]), .update(update[3]));
comp comp4(.in_comp(bcd_reg[19:16]), .update(update[4]));
sum sum0(.in_nibble(bcd_reg[3:0]), .out_nibble(bcd_add[3:0]));
sum sum1(.in_nibble(bcd_reg[7:4]), .out_nibble(bcd_add[7:4]));
sum sum2(.in_nibble(bcd_reg[11:8]), .out_nibble(bcd_add[11:8]));
sum sum3(.in_nibble(bcd_reg[15:12]), .out_nibble(bcd_add[15:12]));
sum sum4(.in_nibble(bcd_reg[19:16]), .out_nibble(bcd_add[19:16]));
counter counter0(.clk(clk), .DEC(DEC), .Load(Load), .Zero(Zero));
control control0(.clk(clk), .rst(rst), .init(init), .Zero(Zero), .Load(Load), .SHFT(SHFT), .add(add), .DEC(DEC), .done(done));
assign BCD=bcd_reg;
    
endmodule

Entrega_Final/bin_bcd/bin2bcd_TB.v
module bin2bcd_TB;
reg clk;
reg rst;
reg init;
reg [15:0] Bin;
wire [19:0] BCD;
wire done;

bin2bcd uut(.clk(clk), .rst(rst), .init(init), .Bin(Bin), .BCD(BCD), .done(done));
initial begin
    clk=0;
    forever #20 clk=~clk;
end
initial begin
    $dumpfile("bin2bcd_TB.vcd");
    $dumpvars(0, bin2bcd_TB);

    rst=1;
    init=0;
    Bin=16'd115;
    @(posedge clk);
    rst=0;
    @(posedge clk);
    init=1;
    @(posedge clk);
    init=0;
    wait(done);
    @(posedge clk);
    rst=1;
    init=0;
    Bin=16'd65535;
    @(posedge clk);
    rst=0;
    init=1;
    @(posedge clk);
    init=0;
    wait(done);
    #20;
    $finish;
end
endmodule

Entrega_Final/bin_bcd/bin2bcd_TB.vcd
$date
	Tue Jul 14 08:45:23 2026
$end
$version
	Icarus Verilog
$end
$timescale
	1s
$end
$scope module bin2bcd_TB $end
$var wire 1 ! done $end
$var wire 20 " BCD [19:0] $end
$var reg 16 # Bin [15:0] $end
$var reg 1 $ clk $end
$var reg 1 % init $end
$var reg 1 & rst $end
$scope module uut $end
$var wire 20 ' BCD [19:0] $end
$var wire 16 ( Bin [15:0] $end
$var wire 1 $ clk $end
$var wire 1 % init $end
$var wire 1 & rst $end
$var wire 5 ) update [4:0] $end
$var wire 1 ! done $end
$var wire 20 * bcd_reg [19:0] $end
$var wire 20 + bcd_add [19:0] $end
$var wire 1 , add $end
$var wire 1 - Zero $end
$var wire 1 . SHFT $end
$var wire 1 / Load $end
$var wire 1 0 DEC $end
$scope module REG0 $end
$var wire 1 $ clk $end
$var wire 16 1 in_Bin [15:0] $end
$var wire 20 2 in_bcd [19:0] $end
$var wire 5 3 update [4:0] $end
$var wire 1 , add $end
$var wire 1 . SHFT $end
$var wire 1 / Load $end
$var wire 20 4 BCD_Out [19:0] $end
$var reg 36 5 alldata [35:0] $end
$upscope $end
$scope module comp0 $end
$var wire 4 6 in_comp [3:0] $end
$var wire 1 7 update $end
$upscope $end
$scope module comp1 $end
$var wire 4 8 in_comp [3:0] $end
$var wire 1 9 update $end
$upscope $end
$scope module comp2 $end
$var wire 4 : in_comp [3:0] $end
$var wire 1 ; update $end
$upscope $end
$scope module comp3 $end
$var wire 4 < in_comp [3:0] $end
$var wire 1 = update $end
$upscope $end
$scope module comp4 $end
$var wire 4 > in_comp [3:0] $end
$var wire 1 ? update $end
$upscope $end
$scope module control0 $end
$var wire 1 $ clk $end
$var wire 1 % init $end
$var wire 1 & rst $end
$var wire 1 - Zero $end
$var parameter 3 @ CHECK_COUNTER $end
$var parameter 3 A ENABLE_SUM $end
$var parameter 3 B FINISH $end
$var parameter 3 C SHIFT_DEC $end
$var parameter 3 D START $end
$var reg 1 0 DEC $end
$var reg 1 / Load $end
$var reg 1 . SHFT $end
$var reg 3 E STATE [2:0] $end
$var reg 1 , add $end
$var reg 6 F counts [5:0] $end
$var reg 1 ! done $end
$var reg 160 G estados [160:1] $end
$upscope $end
$scope module counter0 $end
$var wire 1 0 DEC $end
$var wire 1 / Load $end
$var wire 1 $ clk $end
$var wire 1 - Zero $end
$var reg 5 H count [4:0] $end
$upscope $end
$scope module sum0 $end
$var wire 4 I in_nibble [3:0] $end
$var wire 4 J out_nibble [3:0] $end
$upscope $end
$scope module sum1 $end
$var wire 4 K in_nibble [3:0] $end
$var wire 4 L out_nibble [3:0] $end
$upscope $end
$scope module sum2 $end
$var wire 4 M in_nibble [3:0] $end
$var wire 4 N out_nibble [3:0] $end
$upscope $end
$scope module sum3 $end
$var wire 4 O in_nibble [3:0] $end
$var wire 4 P out_nibble [3:0] $end
$upscope $end
$scope module sum4 $end
$var wire 4 Q in_nibble [3:0] $end
$var wire 4 R out_nibble [3:0] $end
$upscope $end
$upscope $end
$upscope $end
$enddefinitions $end
$comment Show the parameter values. $end
$dumpall
b0 D
b1 C
b100 B
b11 A
b10 @
$end
#0
$dumpvars
bx R
bx Q
bx P
bx O
bx N
bx M
bx L
bx K
bx J
bx I
bx H
b101001101010100010000010101001001010100 G
bx F
b0 E
x?
bx >
x=
bx <
x;
bx :
x9
bx 8
x7
bx 6
bx 5
bx 4
bx 3
bx 2
b1110011 1
00
1/
0.
x-
0,
bx +
bx *
bx )
b1110011 (
bx '
1&
0%
0$
b1110011 #
bx "
0!
$end
#20
b11 R
b0 Q
b11 P
b0 O
b11 N
b0 M
b11 L
b0 K
b110011001100110011 +
b110011001100110011 2
b11 J
b0 I
0?
b0 >
0=
b0 <
0;
b0 :
09
b0 8
b0 )
b0 3
07
b0 6
b0 "
b0 '
b0 *
b0 4
b1110011 5
0-
b10000 H
0&
1$
#40
0$
#60
b0 F
1%
1$
#80
0$
#100
10
1.
0/
b10100110100100001001001010001100101010001011111010001000100010101000011 G
b1 E
0%
1$
#120
0$
#140
b1000011010010000100010101000011010010110101111101000011010011110101010101001110010101000100010101010010 G
00
0.
b1111 H
b11100110 5
b10 E
1$
#160
0$
#180
1,
b1000101010011100100000101000010010011000100010101011111010100110101010101001101 G
b11 E
1$
#200
0$
#220
b10100110100100001001001010001100101010001011111010001000100010101000011 G
10
0,
1.
b1 E
1$
#240
0$
#260
00
0.
b1000011010010000100010101000011010010110101111101000011010011110101010101001110010101000100010101010010 G
b111001100 5
b1110 H
b10 E
1$
#280
0$
#300
b1000101010011100100000101000010010011000100010101011111010100110101010101001101 G
1,
b11 E
1$
#320
0$
#340
10
0,
1.
b10100110100100001001001010001100101010001011111010001000100010101000011 G
b1 E
1$
#360
0$
#380
b1000011010010000100010101000011010010110101111101000011010011110101010101001110010101000100010101010010 G
00
0.
b1101 H
b1110011000 5
b10 E
1$
#400
0$
#420
1,
b1000101010011100100000101000010010011000100010101011111010100110101010101001101 G
b11 E
1$
#440
0$
#460
b10100110100100001001001010001100101010001011111010001000100010101000011 G
10
0,
1.
b1 E
1$
#480
0$
#500
00
0.
b1000011010010000100010101000011010010110101111101000011010011110101010101001110010101000100010101010010 G
b11100110000 5
b1100 H
b10 E
1$
#520
0$
#540
b1000101010011100100000101000010010011000100010101011111010100110101010101001101 G
1,
b11 E
1$
#560
0$
#580
10
0,
1.
b10100110100100001001001010001100101010001011111010001000100010101000011 G
b1 E
1$
#600
0$
#620
b1000011010010000100010101000011010010110101111101000011010011110101010101001110010101000100010101010010 G
00
0.
b1011 H
b111001100000 5
b10 E
1$
#640
0$
#660
1,
b1000101010011100100000101000010010011000100010101011111010100110101010101001101 G
b11 E
1$
#680
0$
#700
b10100110100100001001001010001100101010001011111010001000100010101000011 G
10
0,
1.
b1 E
1$
#720
0$
#740
00
0.
b1000011010010000100010101000011010010110101111101000011010011110101010101001110010101000100010101010010 G
b1110011000000 5
b1010 H
b10 E
1$
#760
0$
#780
b1000101010011100100000101000010010011000100010101011111010100110101010101001101 G
1,
b11 E
1$
#800
0$
#820
10
0,
1.
b10100110100100001001001010001100101010001011111010001000100010101000011 G
b1 E
1$
#840
0$
#860
b1000011010010000100010101000011010010110101111101000011010011110101010101001110010101000100010101010010 G
00
0.
b1001 H
b11100110000000 5
b10 E
1$
#880
0$
#900
1,
b1000101010011100100000101000010010011000100010101011111010100110101010101001101 G
b11 E
1$
#920
0$
#940
b10100110100100001001001010001100101010001011111010001000100010101000011 G
10
0,
1.
b1 E
1$
#960
0$
#980
00
0.
b1000011010010000100010101000011010010110101111101000011010011110101010101001110010101000100010101010010 G
b111001100000000 5
b1000 H
b10 E
1$
#1000
0$
#1020
b1000101010011100100000101000010010011000100010101011111010100110101010101001101 G
1,
b11 E
1$
#1040
0$
#1060
10
0,
1.
b10100110100100001001001010001100101010001011111010001000100010101000011 G
b1 E
1$
#1080
0$
#1100
b1000011010010000100010101000011010010110101111101000011010011110101010101001110010101000100010101010010 G
00
0.
b111 H
b1110011000000000 5
b10 E
1$
#1120
0$
#1140
1,
b1000101010011100100000101000010010011000100010101011111010100110101010101001101 G
b11 E
1$
#1160
0$
#1180
b10100110100100001001001010001100101010001011111010001000100010101000011 G
10
0,
1.
b1 E
1$
#1200
0$
#1220
b110011001100110100 +
b110011001100110100 2
b100 J
b1 I
b1 6
b1 "
b1 '
b1 *
b1 4
00
0.
b1000011010010000100010101000011010010110101111101000011010011110101010101001110010101000100010101010010 G
b11100110000000000 5
b110 H
b10 E
1$
#1240
0$
#1260
b1000101010011100100000101000010010011000100010101011111010100110101010101001101 G
1,
b11 E
1$
#1280
0$
#1300
10
0,
1.
b10100110100100001001001010001100101010001011111010001000100010101000011 G
b1 E
1$
#1320
0$
#1340
b110011001100110110 +
b110011001100110110 2
b110 J
b11 I
b11 6
b11 "
b11 '
b11 *
b11 4
b1000011010010000100010101000011010010110101111101000011010011110101010101001110010101000100010101010010 G
00
0.
b101 H
b111001100000000000 5
b10 E
1$
#1360
0$
#1380
1,
b1000101010011100100000101000010010011000100010101011111010100110101010101001101 G
b11 E
1$
#1400
0$
#1420
b10100110100100001001001010001100101010001011111010001000100010101000011 G
10
0,
1.
b1 E
1$
#1440
0$
#1460
b110011001100111010 +
b110011001100111010 2
b1010 J
b111 I
b1 )
b1 3
17
b111 6
b111 "
b111 '
b111 *
b111 4
00
0.
b1000011010010000100010101000011010010110101111101000011010011110101010101001110010101000100010101010010 G
b1110011000000000000 5
b100 H
b10 E
1$
#1480
0$
#1500
b1000101010011100100000101000010010011000100010101011111010100110101010101001101 G
1,
b11 E
1$
#1520
0$
#1540
b110011001100111101 +
b110011001100111101 2
b1101 J
b1010 I
b1010 6
b1010 "
b1010 '
b1010 *
b1010 4
10
0,
1.
b10100110100100001001001010001100101010001011111010001000100010101000011 G
b10100011000000000000 5
b1 E
1$
#1560
0$
#1580
b100 L
b1 K
b110011001101000111 +
b110011001101000111 2
b111 J
b100 I
b1 8
b0 )
b0 3
07
b100 6
b10100 "
b10100 '
b10100 *
b10100 4
b1000011010010000100010101000011010010110101111101000011010011110101010101001110010101000100010101010010 G
00
0.
b11 H
b101000110000000000000 5
b10 E
1$
#1600
0$
#1620
1,
b1000101010011100100000101000010010011000100010101011111010100110101010101001101 G
b11 E
1$
#1640
0$
#1660
b10100110100100001001001010001100101010001011111010001000100010101000011 G
10
0,
1.
b1 E
1$
#1680
0$
#1700
b101 L
b10 K
b110011001101011011 +
b110011001101011011 2
b1011 J
b1000 I
b10 8
b1 )
b1 3
17
b1000 6
b101000 "
b101000 '
b101000 *
b101000 4
00
0.
b1000011010010000100010101000011010010110101111101000011010011110101010101001110010101000100010101010010 G
b1010001100000000000000 5
b10 H
b10 E
1$
#1720
0$
#1740
b1000101010011100100000101000010010011000100010101011111010100110101010101001101 G
1,
b11 E
1$
#1760
0$
#1780
b110011001101011110 +
b110011001101011110 2
b1110 J
b1011 I
b1011 6
b101011 "
b101011 '
b101011 *
b101011 4
10
0,
1.
b10100110100100001001001010001100101010001011111010001000100010101000011 G
b1010111100000000000000 5
b1 E
1$
#1800
0$
#1820
b1000 L
b101 K
b110011001110001010 +
b110011001110001010 2
b1010 J
b111 I
b11 )
b11 3
19
b101 8
b111 6
b1010111 "
b1010111 '
b1010111 *
b1010111 4
b1000011010010000100010101000011010010110101111101000011010011110101010101001110010101000100010101010010 G
00
0.
b1 H
b10101111000000000000000 5
b10 E
1$
#1840
0$
#1860
1,
b1000101010011100100000101000010010011000100010101011111010100110101010101001101 G
b11 E
1$
#1880
0$
#1900
b1011 L
b1000 K
b110011001110111101 +
b110011001110111101 2
b1101 J
b1010 I
b1000 8
b1010 6
b10001010 "
b10001010 '
b10001010 *
b10001010 4
b10100110100100001001001010001100101010001011111010001000100010101000011 G
10
0,
1.
b100010101000000000000000 5
b1 E
1$
#1920
0$
#1940
b100 N
b1 M
b100 L
b1 K
b110011010001001000 +
b110011010001001000 2
b1000 J
b101 I
b1 :
b1 )
b1 3
09
b1 8
b101 6
b100010101 "
b100010101 '
b100010101 *
b100010101 4
00
0.
b1000011010010000100010101000011010010110101111101000011010011110101010101001110010101000100010101010010 G
b1000101010000000000000000 5
1-
b0 H
b10 E
1$
#1960
0$
#1980
b10001100100100101001110010010010101001101001000 G
1!
b100 E
1$
#2000
0$
#2020
0!
1/
b101001101010100010000010101001001010100 G
b0 E
b1 F
b1111111111111111 #
b1111111111111111 (
b1111111111111111 1
1&
1$
#2040
0$
#2060
b11 N
b0 M
b11 L
b0 K
b110011001100110011 +
b110011001100110011 2
b11 J
b0 I
b0 :
b0 8
b0 )
b0 3
07
b0 6
b0 "
b0 '
b0 *
b0 4
0-
b10000 H
b1111111111111111 5
1%
0&
1$
#2080
0$
#2100
b10100110100100001001001010001100101010001011111010001000100010101000011 G
10
1.
0/
b1 E
b0 F
0%
1$
#2120
0$
#2140
b110011001100110100 +
b110011001100110100 2
b100 J
b1 I
b1 6
b1 "
b1 '
b1 *
b1 4
00
0.
b1000011010010000100010101000011010010110101111101000011010011110101010101001110010101000100010101010010 G
b1111 H
b11111111111111110 5
b10 E
1$
#2160
0$
#2180
b1000101010011100100000101000010010011000100010101011111010100110101010101001101 G
1,
b11 E
1$
#2200
0$
#2220
10
0,
1.
b10100110100100001001001010001100101010001011111010001000100010101000011 G
b1 E
1$
#2240
0$
#2260
b110011001100110110 +
b110011001100110110 2
b110 J
b11 I
b11 6
b11 "
b11 '
b11 *
b11 4
b1000011010010000100010101000011010010110101111101000011010011110101010101001110010101000100010101010010 G
00
0.
b111111111111111100 5
b1110 H
b10 E
1$
#2280
0$
#2300
1,
b1000101010011100100000101000010010011000100010101011111010100110101010101001101 G
b11 E
1$
#2320
0$
#2340
b10100110100100001001001010001100101010001011111010001000100010101000011 G
10
0,
1.
b1 E
1$
#2360
0$
#2380
b110011001100111010 +
b110011001100111010 2
b1010 J
b111 I
b1 )
b1 3
17
b111 6
b111 "
b111 '
b111 *
b111 4
00
0.
b1000011010010000100010101000011010010110101111101000011010011110101010101001110010101000100010101010010 G
b1101 H
b1111111111111111000 5
b10 E
1$
#2400
0$
#2420
b1000101010011100100000101000010010011000100010101011111010100110101010101001101 G
1,
b11 E
1$
#2440
0$
#2460
b110011001100111101 +
b110011001100111101 2
b1101 J
b1010 I
b1010 6
b1010 "
b1010 '
b1010 *
b1010 4
10
0,
1.
b10100110100100001001001010001100101010001011111010001000100010101000011 G
b10101111111111111000 5
b1 E
1$
#2480
0$
#2500
b100 L
b1 K
b110011001101001000 +
b110011001101001000 2
b1000 J
b101 I
b1 8
b101 6
b10101 "
b10101 '
b10101 *
b10101 4
b1000011010010000100010101000011010010110101111101000011010011110101010101001110010101000100010101010010 G
00
0.
b101011111111111110000 5
b1100 H
b10 E
1$
#2520
0$
#2540
1,
b1000101010011100100000101000010010011000100010101011111010100110101010101001101 G
b11 E
1$
#2560
0$
#2580
b110011001101001011 +
b110011001101001011 2
b1011 J
b1000 I
b1000 6
b11000 "
b11000 '
b11000 *
b11000 4
b10100110100100001001001010001100101010001011111010001000100010101000011 G
10
0,
1.
b110001111111111110000 5
b1 E
1$
#2600
0$
#2620
b110 L
b11 K
b110011001101100100 +
b110011001101100100 2
b100 J
b1 I
b11 8
b0 )
b0 3
07
b1 6
b110001 "
b110001 '
b110001 *
b110001 4
00
0.
b1000011010010000100010101000011010010110101111101000011010011110101010101001110010101000100010101010010 G
b1011 H
b1100011111111111100000 5
b10 E
1$
#2640
0$
#2660
b1000101010011100100000101000010010011000100010101011111010100110101010101001101 G
1,
b11 E
1$
#2680
0$
#2700
10
0,
1.
b10100110100100001001001010001100101010001011111010001000100010101000011 G
b1 E
1$
#2720
0$
#2740
b1001 L
b110 K
b110011001110010110 +
b110011001110010110 2
b110 J
b11 I
b10 )
b10 3
19
b110 8
b11 6
b1100011 "
b1100011 '
b1100011 *
b1100011 4
b1000011010010000100010101000011010010110101111101000011010011110101010101001110010101000100010101010010 G
00
0.
b11000111111111111000000 5
b1010 H
b10 E
1$
#2760
0$
#2780
1,
b1000101010011100100000101000010010011000100010101011111010100110101010101001101 G
b11 E
1$
#2800
0$
#2820
b110011001111000110 +
b110011001111000110 2
b1100 L
b1001 K
b1001 8
b10010011 "
b10010011 '
b10010011 *
b10010011 4
b10100110100100001001001010001100101010001011111010001000100010101000011 G
10
0,
1.
b100100111111111111000000 5
b1 E
1$
#2840
0$
#2860
b100 N
b1 M
b101 L
b10 K
b110011010001011010 +
b110011010001011010 2
b1010 J
b111 I
b1 :
09
b10 8
b1 )
b1 3
17
b111 6
b100100111 "
b100100111 '
b100100111 *
b100100111 4
00
0.
b1000011010010000100010101000011010010110101111101000011010011110101010101001110010101000100010101010010 G
b1001 H
b1001001111111111110000000 5
b10 E
1$
#2880
0$
#2900
b1000101010011100100000101000010010011000100010101011111010100110101010101001101 G
1,
b11 E
1$
#2920
0$
#2940
b110011010001011101 +
b110011010001011101 2
b1101 J
b1010 I
b1010 6
b100101010 "
b100101010 '
b100101010 *
b100101010 4
10
0,
1.
b10100110100100001001001010001100101010001011111010001000100010101000011 G
b1001010101111111110000000 5
b1 E
1$
#2960
0$
#2980
b101 N
b10 M
b1000 L
b101 K
b110011010110001000 +
b110011010110001000 2
b1000 J
b101 I
b10 :
b11 )
b11 3
19
b101 8
b101 6
b1001010101 "
b1001010101 '
b1001010101 *
b1001010101 4
b1000011010010000100010101000011010010110101111101000011010011110101010101001110010101000100010101010010 G
00
0.
b10010101011111111100000000 5
b1000 H
b10 E
1$
#3000
0$
#3020
1,
b1000101010011100100000101000010010011000100010101011111010100110101010101001101 G
b11 E
1$
#3040
0$
#3060
b1011 L
b1000 K
b110011010110111011 +
b110011010110111011 2
b1011 J
b1000 I
b1000 8
b1000 6
b1010001000 "
b1010001000 '
b1010001000 *
b1010001000 4
b10100110100100001001001010001100101010001011111010001000100010101000011 G
10
0,
1.
b10100010001111111100000000 5
b1 E
1$
#3080
0$
#3100
b1000 N
b101 M
b100 L
b1 K
b110011100001000100 +
b110011100001000100 2
b100 J
b1 I
1;
b101 :
09
b1 8
b100 )
b100 3
07
b1 6
b10100010001 "
b10100010001 '
b10100010001 *
b10100010001 4
00
0.
b1000011010010000100010101000011010010110101111101000011010011110101010101001110010101000100010101010010 G
b111 H
b101000100011111111000000000 5
b10 E
1$
#3120
0$
#3140
b1000101010011100100000101000010010011000100010101011111010100110101010101001101 G
1,
b11 E
1$
#3160
0$
#3180
b110011101101000100 +
b110011101101000100 2
b1011 N
b1000 M
b1000 :
b100000010001 "
b100000010001 '
b100000010001 *
b100000010001 4
10
0,
1.
b10100110100100001001001010001100101010001011111010001000100010101000011 G
b1000000100011111111000000000 5
b1 E
1$
#3200
0$
#3220
b100 P
b1 O
b11 N
b0 M
b101 L
b10 K
b110100001101010110 +
b110100001101010110 2
b110 J
b11 I
b1 <
b0 )
b0 3
0;
b0 :
b10 8
b11 6
b1000000100011 "
b1000000100011 '
b1000000100011 *
b1000000100011 4
b1000011010010000100010101000011010010110101111101000011010011110101010101001110010101000100010101010010 G
00
0.
b10000001000111111110000000000 5
b110 H
b10 E
1$
#3240
0$
#3260
1,
b1000101010011100100000101000010010011000100010101011111010100110101010101001101 G
b11 E
1$
#3280
0$
#3300
b10100110100100001001001010001100101010001011111010001000100010101000011 G
10
0,
1.
b1 E
1$
#3320
0$
#3340
b101 P
b10 O
b111 L
b100 K
b110101001101111010 +
b110101001101111010 2
b1010 J
b111 I
b10 <
b100 8
b1 )
b1 3
17
b111 6
b10000001000111 "
b10000001000111 '
b10000001000111 *
b10000001000111 4
00
0.
b1000011010010000100010101000011010010110101111101000011010011110101010101001110010101000100010101010010 G
b101 H
b100000010001111111100000000000 5
b10 E
1$
#3360
0$
#3380
b1000101010011100100000101000010010011000100010101011111010100110101010101001101 G
1,
b11 E
1$
#3400
0$
#3420
b110101001101111101 +
b110101001101111101 2
b1101 J
b1010 I
b1010 6
b10000001001010 "
b10000001001010 '
b10000001001010 *
b10000001001010 4
10
0,
1.
b10100110100100001001001010001100101010001011111010001000100010101000011 G
b100000010010101111100000000000 5
b1 E
1$
#3440
0$
#3460
b111 P
b100 O
b1100 L
b1001 K
b110111001111001000 +
b110111001111001000 2
b1000 J
b101 I
b100 <
b11 )
b11 3
19
b1001 8
b101 6
b100000010010101 "
b100000010010101 '
b100000010010101 *
b100000010010101 4
b1000011010010000100010101000011010010110101111101000011010011110101010101001110010101000100010101010010 G
00
0.
b1000000100101011111000000000000 5
b100 H
b10 E
1$
#3480
0$
#3500
1,
b1000101010011100100000101000010010011000100010101011111010100110101010101001101 G
b11 E
1$
#3520
0$
#3540
b1111 L
b1100 K
b110111001111111011 +
b110111001111111011 2
b1011 J
b1000 I
b1100 8
b1000 6
b100000011001000 "
b100000011001000 '
b100000011001000 *
b100000011001000 4
b10100110100100001001001010001100101010001011111010001000100010101000011 G
10
0,
1.
b1000000110010001111000000000000 5
b1 E
1$
#3560
0$
#3580
b1011 P
b1000 O
b100 N
b1 M
b1100 L
b1001 K
b111011010011000100 +
b111011010011000100 2
b100 J
b1 I
1=
b1000 <
b1 :
b1001 8
b1010 )
b1010 3
07
b1 6
b1000000110010001 "
b1000000110010001 '
b1000000110010001 *
b1000000110010001 4
00
0.
b1000011010010000100010101000011010010110101111101000011010011110101010101001110010101000100010101010010 G
b11 H
b10000001100100011110000000000000 5
b10 E
1$
#3600
0$
#3620
b1000101010011100100000101000010010011000100010101011111010100110101010101001101 G
1,
b11 E
1$
#3640
0$
#3660
b1110 P
b1011 O
b111110010011110100 +
b111110010011110100 2
b1111 L
b1100 K
b1011 <
b1100 8
b1011000111000001 "
b1011000111000001 '
b1011000111000001 *
b1011000111000001 4
10
0,
1.
b10100110100100001001001010001100101010001011111010001000100010101000011 G
b10110001110000011110000000000000 5
b1 E
1$
#3680
0$
#3700
b100 R
b1 Q
b1001 P
b110 O
b110 N
b11 M
b1011 L
b1000 K
b1001001011010110110 +
b1001001011010110110 2
b110 J
b11 I
b1 >
b110 <
b11 :
b1000 8
b11 6
b10110001110000011 "
b10110001110000011 '
b10110001110000011 *
b10110001110000011 4
b1000011010010000100010101000011010010110101111101000011010011110101010101001110010101000100010101010010 G
00
0.
b101100011100000111100000000000000 5
b10 H
b10 E
1$
#3720
0$
#3740
1,
b1000101010011100100000101000010010011000100010101011111010100110101010101001101 G
b11 E
1$
#3760
0$
#3780
b1100 P
b1001 O
b1001100011011100110 +
b1001100011011100110 2
b1110 L
b1011 K
b1001 <
b1011 8
b11001001110110011 "
b11001001110110011 '
b11001001110110011 *
b11001001110110011 4
b10100110100100001001001010001100101010001011111010001000100010101000011 G
10
0,
1.
b110010011101100111100000000000000 5
b1 E
1$
#3800
0$
#3820
b110 R
b11 Q
b101 P
b10 O
b1010 N
b111 M
b1001 L
b110 K
b1100101101010011010 +
b1100101101010011010 2
b1010 J
b111 I
b11 >
0=
b10 <
1;
b111 :
b110 8
b111 )
b111 3
17
b111 6
b110010011101100111 "
b110010011101100111 '
b110010011101100111 *
b110010011101100111 4
00
0.
b1000011010010000100010101000011010010110101111101000011010011110101010101001110010101000100010101010010 G
b1 H
b1100100111011001111000000000000000 5
b10 E
1$
#3840
0$
#3860
b1000101010011100100000101000010010011000100010101011111010100110101010101001101 G
1,
b11 E
1$
#3880
0$
#3900
b1101 N
b1010 M
b1100 L
b1001 K
b1100101110111001101 +
b1100101110111001101 2
b1101 J
b1010 I
b1010 :
b1001 8
b1010 6
b110010101010011010 "
b110010101010011010 '
b110010101010011010 *
b110010101010011010 4
10
0,
1.
b10100110100100001001001010001100101010001011111010001000100010101000011 G
b1100101010100110101000000000000000 5
b1 E
1$
#3920
0$
#3940
b1001 R
b110 Q
b1000 P
b101 O
b1000 N
b101 M
b110 L
b11 K
b10011000100001101000 +
b10011000100001101000 2
b1000 J
b101 I
1?
b110 >
1=
b101 <
b101 :
b11101 )
b11101 3
09
b11 8
b101 6
b1100101010100110101 "
b1100101010100110101 '
b1100101010100110101 *
b1100101010100110101 4
b1000011010010000100010101000011010010110101111101000011010011110101010101001110010101000100010101010010 G
00
0.
b11001010101001101010000000000000000 5
1-
b0 H
b10 E
1$
#3960
0$
#3980
1!
b10001100100100101001110010010010101001101001000 G
b100 E
1$
