Entrega_Final/bcd_bin/control.v
module control (clk, init, Zero, rst, Load, SHFT, subtract, DEC, done);
    input clk;
    input init;
    input Zero;
    input rst;
    output reg Load;
    output reg SHFT;
    output reg subtract;
    output reg DEC;
    output reg done;

parameter  START = 3'b000;
parameter  Check_counter = 3'b001;
parameter  Subtract3 = 3'b010;
parameter  Shift_dec = 3'b011;
parameter  Finish = 3'b100;

reg [2:0] STATE;
reg [5:0] counts;

always @(posedge clk or posedge rst) 
begin
    if (rst) 
    begin
        STATE <= START;
    end
    else begin
        case (STATE)
            START:
            begin
                counts <=0;
                if (init)
                    STATE <= Shift_dec;
                else
                    STATE <= START;
            end
            Shift_dec:
            begin
                STATE <= Check_counter;
            end
            Check_counter:
            begin
                if (Zero)
                    STATE <= Finish;
                else
                    STATE <=Subtract3;
            end
            Subtract3:
            begin
                STATE <= Shift_dec;
            end
            Finish:
            begin
                counts <=(counts+1);
                if (counts >=28)
                    STATE<= START;
                else
                    STATE <= Finish;
            end
            default:
                STATE<=START; 
        endcase
    end
end
always @(*) 
begin
    case (STATE)
        START:
        begin
            SHFT = 0;
            Load = 1;
            subtract = 0;
            DEC = 0;
            done = 0;
        end
        Check_counter:
        begin
            SHFT = 0;
            Load = 0;
            subtract = 0;
            DEC = 0;
            done = 0;
        end
        Subtract3:
        begin
            SHFT = 0;
            Load = 0;
            subtract = 1;
            DEC = 0;
            done = 0;
        end
        Shift_dec:
        begin
            SHFT = 1;
            Load = 0;
            subtract = 0;
            DEC = 1;
            done = 0;
        end
        Finish:
        begin
            SHFT = 0;
            Load = 0;
            subtract = 0;
            DEC = 0;
            done = 1;
        end
        default:
        begin
            SHFT = 0;
            Load = 0;
            subtract = 0;
            DEC = 0;
            done = 0; 
        end
    endcase    
end
`ifdef BENCH
reg [8*20:1] estados;
always @(*) begin
    case (STATE)
        START: estados="START";
        Shift_dec: estados="SHIFT_DEC";
        Check_counter: estados="CHECK_COUNTER";
        Subtract3: estados="SUBTRACT3";
        Finish: estados="FINISH";
        default: estados="unknown";
    endcase
end
`endif
endmodule

Entrega_Final/bcd_bin/counter.v
module counter (clk, DEC, Load, Zero);
input clk;
input DEC;
input Load;
reg [4:0] count;
output Zero;
assign Zero = (count==0);
always @(posedge clk) begin
    if (Load) 
    begin
        count <= 5'd16;    
    end
    else if (DEC)
        count <= (count - 1);    
end


endmodule

Entrega_Final/bcd_bin/subtractor.v
module subtractor (in_nibble, sub_bcd);
input [3:0] in_nibble;
output[3:0] sub_bcd;
assign sub_bcd = in_nibble - 4'd3;
endmodule

Entrega_Final/bcd_bin/comp.v
module comp (in_comp, update);
input [3:0]in_comp;
output update;
assign update = (in_comp >= 4'd8);
endmodule

Entrega_Final/bcd_bin/combrsr.v
module combrsr (clk, Load, SHFT, subtract, update, in_bcd, sub_bcd, Bin_out, BCD_out);
    input clk;
    input Load;
    input SHFT;
    input subtract;
    input [4:0]update;
    input [19:0]in_bcd;
    input [19:0]sub_bcd;
    output [15:0]Bin_out;
    output [19:0]BCD_out;

    reg [35:0]alldata;
    assign Bin_out=alldata[15:0];
    assign BCD_out=alldata[35:16];

always @(posedge clk) begin
    if (Load) 
    begin
        alldata[35:16] <= in_bcd;
        alldata[15:0] <= 16'b0;    
    end
    else if (SHFT) 
    begin
        alldata <= alldata >> 1;    
    end
    else if (subtract) 
    begin
        if (update[4]) 
            alldata[35:32] <= sub_bcd[19:16];
        if (update[3]) 
            alldata[31:28] <= sub_bcd[15:12];
        if (update[2]) 
            alldata[27:24] <= sub_bcd[11:8];
        if (update[1]) 
            alldata[23:20] <= sub_bcd[7:4];
        if (update[0]) 
            alldata[19:16] <= sub_bcd[3:0];
    end
end
endmodule

Entrega_Final/bcd_bin/bcd_bin.v
module bcd_bin(clk, rst, init, BCD, Bin, done);
input clk;
input rst;
input init;
input [19:0]BCD;
output [15:0]Bin;
output done;
wire Load;
wire SHFT;
wire subtract;
wire DEC;
wire Zero;
wire [19:0] bcd_reg;
wire [19:0] sub_bcd;
wire [4:0] update;

combrsr combrsr0(.clk(clk), .Load(Load), .SHFT(SHFT), .subtract(subtract), .update(update), .in_bcd(BCD), .sub_bcd(sub_bcd), .Bin_out(Bin), .BCD_out(bcd_reg));
comp comp0(.in_comp(bcd_reg[3:0]), .update(update[0]));
comp comp1(.in_comp(bcd_reg[7:4]), .update(update[1]));
comp comp2(.in_comp(bcd_reg[11:8]), .update(update[2]));
comp comp3(.in_comp(bcd_reg[15:12]), .update(update[3]));
comp comp4(.in_comp(bcd_reg[19:16]), .update(update[4]));
subtractor sub0(.in_nibble(bcd_reg[3:0]), .sub_bcd(sub_bcd[3:0]));
subtractor sub1(.in_nibble(bcd_reg[7:4]), .sub_bcd(sub_bcd[7:4]));
subtractor sub2(.in_nibble(bcd_reg[11:8]), .sub_bcd(sub_bcd[11:8]));
subtractor sub3(.in_nibble(bcd_reg[15:12]), .sub_bcd(sub_bcd[15:12]));
subtractor sub4(.in_nibble(bcd_reg[19:16]), .sub_bcd(sub_bcd[19:16]));
counter counter0(.clk(clk), .DEC(DEC), .Load(Load), .Zero(Zero));
control control0(.clk(clk), .init(init), .Zero(Zero), .rst(rst), .Load(Load), .SHFT(SHFT), .subtract(subtract), .DEC(DEC), .done(done));

   
endmodule

Entrega_Final/bcd_bin/bcd_bin_TB.v
module bcd2bin_TB;
reg clk;
reg rst;
reg init;
reg [19:0]BCD;
wire [15:0]Bin;
wire done;

bcd_bin uut(.clk(clk), .rst(rst), .init(init), .BCD(BCD), .Bin(Bin), .done(done));

initial begin
    clk=0;
    forever #20 clk = ~clk;
end
initial begin
    $dumpfile("bcd2bin_TB.vcd");
    $dumpvars(0, bcd2bin_TB);
    rst=1;
    init=0;
    BCD=20'h11111;
    @(posedge clk);
    rst=0;
    init=1;
    @(posedge clk);
    init=0;
    wait(done);
    #40;
    BCD=20'h00000;
    rst=1;
    @(posedge clk);
    rst=0;
    init=1;
    @(posedge clk);
    init=0;
    wait(done);
    #40;
    rst=1;
    BCD=20'h99;
    init=0;
    @(posedge clk);
    rst=0;
    init=1;
    @(posedge clk);
    init=0;
    wait(done)
    #40;
    rst=1;
    BCD=20'h81;
    init=0;
    @(posedge clk);
    init=1;
    rst=0;
    @(posedge clk);
    init=0;
    wait(done);
    #40;
    rst=1;
    BCD=20'h8888;
    init=0;
    @(posedge clk);
    init=1;
    rst=0;
    @(posedge clk);
    init=0;
    wait(done);
    #40;
    rst=1;
    BCD=20'h23987;
    init=0;
    @(posedge clk);
    init=1;
    rst=0;
    @(posedge clk);
    init=0;
    wait(done);
    $finish;
end
    
endmodule

Entrega_Final/bcd_bin/bcd2bin_TB.vcd
$date
	Tue Jul 14 08:43:45 2026
$end
$version
	Icarus Verilog
$end
$timescale
	1s
$end
$scope module bcd2bin_TB $end
$var wire 1 ! done $end
$var wire 16 " Bin [15:0] $end
$var reg 20 # BCD [19:0] $end
$var reg 1 $ clk $end
$var reg 1 % init $end
$var reg 1 & rst $end
$scope module uut $end
$var wire 20 ' BCD [19:0] $end
$var wire 1 $ clk $end
$var wire 1 % init $end
$var wire 1 & rst $end
$var wire 5 ( update [4:0] $end
$var wire 1 ) subtract $end
$var wire 20 * sub_bcd [19:0] $end
$var wire 1 ! done $end
$var wire 20 + bcd_reg [19:0] $end
$var wire 1 , Zero $end
$var wire 1 - SHFT $end
$var wire 1 . Load $end
$var wire 1 / DEC $end
$var wire 16 0 Bin [15:0] $end
$scope module combrsr0 $end
$var wire 1 $ clk $end
$var wire 20 1 in_bcd [19:0] $end
$var wire 20 2 sub_bcd [19:0] $end
$var wire 5 3 update [4:0] $end
$var wire 1 ) subtract $end
$var wire 1 - SHFT $end
$var wire 1 . Load $end
$var wire 16 4 Bin_out [15:0] $end
$var wire 20 5 BCD_out [19:0] $end
$var reg 36 6 alldata [35:0] $end
$upscope $end
$scope module comp0 $end
$var wire 4 7 in_comp [3:0] $end
$var wire 1 8 update $end
$upscope $end
$scope module comp1 $end
$var wire 4 9 in_comp [3:0] $end
$var wire 1 : update $end
$upscope $end
$scope module comp2 $end
$var wire 4 ; in_comp [3:0] $end
$var wire 1 < update $end
$upscope $end
$scope module comp3 $end
$var wire 4 = in_comp [3:0] $end
$var wire 1 > update $end
$upscope $end
$scope module comp4 $end
$var wire 4 ? in_comp [3:0] $end
$var wire 1 @ update $end
$upscope $end
$scope module control0 $end
$var wire 1 $ clk $end
$var wire 1 % init $end
$var wire 1 & rst $end
$var wire 1 , Zero $end
$var parameter 3 A Check_counter $end
$var parameter 3 B Finish $end
$var parameter 3 C START $end
$var parameter 3 D Shift_dec $end
$var parameter 3 E Subtract3 $end
$var reg 1 / DEC $end
$var reg 1 . Load $end
$var reg 1 - SHFT $end
$var reg 3 F STATE [2:0] $end
$var reg 6 G counts [5:0] $end
$var reg 1 ! done $end
$var reg 160 H estados [160:1] $end
$var reg 1 ) subtract $end
$upscope $end
$scope module counter0 $end
$var wire 1 / DEC $end
$var wire 1 . Load $end
$var wire 1 $ clk $end
$var wire 1 , Zero $end
$var reg 5 I count [4:0] $end
$upscope $end
$scope module sub0 $end
$var wire 4 J in_nibble [3:0] $end
$var wire 4 K sub_bcd [3:0] $end
$upscope $end
$scope module sub1 $end
$var wire 4 L in_nibble [3:0] $end
$var wire 4 M sub_bcd [3:0] $end
$upscope $end
$scope module sub2 $end
$var wire 4 N in_nibble [3:0] $end
$var wire 4 O sub_bcd [3:0] $end
$upscope $end
$scope module sub3 $end
$var wire 4 P in_nibble [3:0] $end
$var wire 4 Q sub_bcd [3:0] $end
$upscope $end
$scope module sub4 $end
$var wire 4 R in_nibble [3:0] $end
$var wire 4 S sub_bcd [3:0] $end
$upscope $end
$upscope $end
$upscope $end
$enddefinitions $end
$comment Show the parameter values. $end
$dumpall
b10 E
b11 D
b0 C
b100 B
b1 A
$end
#0
$dumpvars
bx S
bx R
bx Q
bx P
bx O
bx N
bx M
bx L
bx K
bx J
bx I
b101001101010100010000010101001001010100 H
bx G
b0 F
x@
bx ?
x>
bx =
x<
bx ;
x:
bx 9
x8
bx 7
bx 6
bx 5
bx 4
bx 3
bx 2
b10001000100010001 1
bx 0
0/
1.
0-
x,
bx +
bx *
0)
bx (
b10001000100010001 '
1&
0%
0$
b10001000100010001 #
bx "
0!
$end
#20
b1110 S
b1 R
b1110 Q
b1 P
b1110 O
b1 N
b1110 M
b1 L
b11101110111011101110 *
b11101110111011101110 2
b1110 K
b1 J
0@
b1 ?
0>
b1 =
0<
b1 ;
0:
b1 9
b0 (
b0 3
08
b1 7
b0 "
b0 0
b0 4
b10001000100010001 +
b10001000100010001 5
b100010001000100010000000000000000 6
0,
b10000 I
1%
0&
1$
#40
0$
#60
1/
0.
1-
b10100110100100001001001010001100101010001011111010001000100010101000011 H
b11 F
b0 G
0%
1$
#80
0$
#100
b1101 S
b0 R
b101 Q
b1000 P
b101 O
b1000 N
b101 M
b1000 L
b11010101010101010101 *
b11010101010101010101 2
b101 K
b1000 J
b0 ?
1>
b1000 =
1<
b1000 ;
1:
b1000 9
b1111 (
b1111 3
18
b1000 7
b1000000000000000 "
b1000000000000000 0
b1000000000000000 4
b1000100010001000 +
b1000100010001000 5
b1000011010010000100010101000011010010110101111101000011010011110101010101001110010101000100010101010010 H
0/
0-
b10001000100010001000000000000000 6
b1111 I
b1 F
1$
#120
0$
#140
1)
b10100110101010101000010010101000101001001000001010000110101010000110011 H
b10 F
1$
#160
0$
#180
b10 Q
b101 P
b10 O
b101 N
b10 M
b101 L
b11010010001000100010 *
b11010010001000100010 2
b10 K
b101 J
0>
b101 =
0<
b101 ;
0:
b101 9
b0 (
b0 3
08
b101 7
b101010101010101 +
b101010101010101 5
b10100110100100001001001010001100101010001011111010001000100010101000011 H
1/
0)
1-
b1010101010101011000000000000000 6
b11 F
1$
#200
0$
#220
b1111 Q
b10 P
b111 O
b1010 N
b111 M
b1010 L
b11011111011101110111 *
b11011111011101110111 2
b111 K
b1010 J
b10 =
1<
b1010 ;
1:
b1010 9
b111 (
b111 3
18
b1010 7
b1100000000000000 "
b1100000000000000 0
b1100000000000000 4
b10101010101010 +
b10101010101010 5
0/
0-
b1000011010010000100010101000011010010110101111101000011010011110101010101001110010101000100010101010010 H
b1110 I
b101010101010101100000000000000 6
b1 F
1$
#240
0$
#260
b10100110101010101000010010101000101001001000001010000110101010000110011 H
1)
b10 F
1$
#280
0$
#300
b100 O
b111 N
b100 M
b111 L
b11011111010001000100 *
b11011111010001000100 2
b100 K
b111 J
0<
b111 ;
0:
b111 9
b0 (
b0 3
08
b111 7
b10011101110111 +
b10011101110111 5
1/
0)
1-
b10100110100100001001001010001100101010001011111010001000100010101000011 H
b100111011101111100000000000000 6
b11 F
1$
#320
0$
#340
b1110 Q
b1 P
b0 O
b11 N
b1000 M
b1011 L
b11011110000010001000 *
b11011110000010001000 2
b1000 K
b1011 J
b1 =
b11 ;
1:
b1011 9
b11 (
b11 3
18
b1011 7
b1110000000000000 "
b1110000000000000 0
b1110000000000000 4
b1001110111011 +
b1001110111011 5
b1000011010010000100010101000011010010110101111101000011010011110101010101001110010101000100010101010010 H
0/
0-
b10011101110111110000000000000 6
b1101 I
b1 F
1$
#360
0$
#380
1)
b10100110101010101000010010101000101001001000001010000110101010000110011 H
b10 F
1$
#400
0$
#420
b101 M
b1000 L
b11011110000001010101 *
b11011110000001010101 2
b101 K
b1000 J
b1000 9
b1000 7
b1001110001000 +
b1001110001000 5
b10100110100100001001001010001100101010001011111010001000100010101000011 H
1/
0)
1-
b10011100010001110000000000000 6
b11 F
1$
#440
0$
#460
b1101 Q
b0 P
b110 O
b1001 N
b1001 M
b1100 L
b11011101011010010001 *
b11011101011010010001 2
b1 K
b100 J
b0 =
1<
b1001 ;
b1100 9
b110 (
b110 3
08
b100 7
b111000000000000 "
b111000000000000 0
b111000000000000 4
b100111000100 +
b100111000100 5
0/
0-
b1000011010010000100010101000011010010110101111101000011010011110101010101001110010101000100010101010010 H
b1100 I
b1001110001000111000000000000 6
b1 F
1$
#480
0$
#500
b10100110101010101000010010101000101001001000001010000110101010000110011 H
1)
b10 F
1$
#520
0$
#540
b11 O
b110 N
b11011101001101100001 *
b11011101001101100001 2
b110 M
b1001 L
b10 (
b10 3
0<
b110 ;
b1001 9
b11010010100 +
b11010010100 5
1/
0)
1-
b10100110100100001001001010001100101010001011111010001000100010101000011 H
b110100101000111000000000000 6
b11 F
1$
#560
0$
#580
b0 O
b11 N
b1 M
b100 L
b11011101000000010111 *
b11011101000000010111 2
b111 K
b1010 J
b11 ;
0:
b100 9
b1 (
b1 3
18
b1010 7
b11100000000000 "
b11100000000000 0
b11100000000000 4
b1101001010 +
b1101001010 5
b1000011010010000100010101000011010010110101111101000011010011110101010101001110010101000100010101010010 H
0/
0-
b11010010100011100000000000 6
b1011 I
b1 F
1$
#600
0$
#620
1)
b10100110101010101000010010101000101001001000001010000110101010000110011 H
b10 F
1$
#640
0$
#660
b11011101000000010100 *
b11011101000000010100 2
b100 K
b111 J
b0 (
b0 3
08
b111 7
b1101000111 +
b1101000111 5
b10100110100100001001001010001100101010001011111010001000100010101000011 H
1/
0)
1-
b11010001110011100000000000 6
b11 F
1$
#680
0$
#700
b1110 O
b1 N
b111 M
b1010 L
b11011101111001110000 *
b11011101111001110000 2
b0 K
b11 J
b1 ;
b10 (
b10 3
1:
b1010 9
b11 7
b1001110000000000 "
b1001110000000000 0
b1001110000000000 4
b110100011 +
b110100011 5
0/
0-
b1000011010010000100010101000011010010110101111101000011010011110101010101001110010101000100010101010010 H
b1010 I
b1101000111001110000000000 6
b1 F
1$
#720
0$
#740
b10100110101010101000010010101000101001001000001010000110101010000110011 H
1)
b10 F
1$
#760
0$
#780
b11011101111001000000 *
b11011101111001000000 2
b100 M
b111 L
b0 (
b0 3
0:
b111 9
b101110011 +
b101110011 5
1/
0)
1-
b10100110100100001001001010001100101010001011111010001000100010101000011 H
b1011100111001110000000000 6
b11 F
1$
#800
0$
#820
b1101 O
b0 N
b1000 M
b1011 L
b11011101110110000110 *
b11011101110110000110 2
b110 K
b1001 J
b0 ;
1:
b1011 9
b11 (
b11 3
18
b1001 7
b1100111000000000 "
b1100111000000000 0
b1100111000000000 4
b10111001 +
b10111001 5
b1000011010010000100010101000011010010110101111101000011010011110101010101001110010101000100010101010010 H
0/
0-
b101110011100111000000000 6
b1001 I
b1 F
1$
#840
0$
#860
1)
b10100110101010101000010010101000101001001000001010000110101010000110011 H
b10 F
1$
#880
0$
#900
b101 M
b1000 L
b11011101110101010011 *
b11011101110101010011 2
b11 K
b110 J
b1000 9
b10 (
b10 3
08
b110 7
b10000110 +
b10000110 5
b10100110100100001001001010001100101010001011111010001000100010101000011 H
1/
0)
1-
b100001101100111000000000 6
b11 F
1$
#920
0$
#940
b1 M
b100 L
b11011101110100010000 *
b11011101110100010000 2
b0 K
b11 J
b0 (
b0 3
0:
b100 9
b11 7
b110011100000000 "
b110011100000000 0
b110011100000000 4
b1000011 +
b1000011 5
0/
0-
b1000011010010000100010101000011010010110101111101000011010011110101010101001110010101000100010101010010 H
b1000 I
b10000110110011100000000 6
b1 F
1$
#960
0$
#980
b10100110101010101000010010101000101001001000001010000110101010000110011 H
1)
b10 F
1$
#1000
0$
#1020
1/
0)
1-
b10100110100100001001001010001100101010001011111010001000100010101000011 H
b11 F
1$
#1040
0$
#1060
b1111 M
b10 L
b11011101110111111110 *
b11011101110111111110 2
b1110 K
b1 J
b10 9
b1 7
b1011001110000000 "
b1011001110000000 0
b1011001110000000 4
b100001 +
b100001 5
b1000011010010000100010101000011010010110101111101000011010011110101010101001110010101000100010101010010 H
0/
0-
b1000011011001110000000 6
b111 I
b1 F
1$
#1080
0$
#1100
1)
b10100110101010101000010010101000101001001000001010000110101010000110011 H
b10 F
1$
#1120
0$
#1140
b10100110100100001001001010001100101010001011111010001000100010101000011 H
1/
0)
1-
b11 F
1$
#1160
0$
#1180
b1110 M
b1 L
b11011101110111101101 *
b11011101110111101101 2
b1101 K
b0 J
b1 9
b0 7
b1101100111000000 "
b1101100111000000 0
b1101100111000000 4
b10000 +
b10000 5
0/
0-
b1000011010010000100010101000011010010110101111101000011010011110101010101001110010101000100010101010010 H
b110 I
b100001101100111000000 6
b1 F
1$
#1200
0$
#1220
b10100110101010101000010010101000101001001000001010000110101010000110011 H
1)
b10 F
1$
#1240
0$
#1260
1/
0)
1-
b10100110100100001001001010001100101010001011111010001000100010101000011 H
b11 F
1$
#1280
0$
#1300
b1101 M
b0 L
b11011101110111010101 *
b11011101110111010101 2
b101 K
b1000 J
b0 9
b1 (
b1 3
18
b1000 7
b110110011100000 "
b110110011100000 0
b110110011100000 4
b1000 +
b1000 5
b1000011010010000100010101000011010010110101111101000011010011110101010101001110010101000100010101010010 H
0/
0-
b10000110110011100000 6
b101 I
b1 F
1$
#1320
0$
#1340
1)
b10100110101010101000010010101000101001001000001010000110101010000110011 H
b10 F
1$
#1360
0$
#1380
b11011101110111010010 *
b11011101110111010010 2
b10 K
b101 J
b0 (
b0 3
08
b101 7
b101 +
b101 5
b10100110100100001001001010001100101010001011111010001000100010101000011 H
1/
0)
1-
b1010110110011100000 6
b11 F
1$
#1400
0$
#1420
b11011101110111011111 *
b11011101110111011111 2
b1111 K
b10 J
b10 7
b1011011001110000 "
b1011011001110000 0
b1011011001110000 4
b10 +
b10 5
0/
0-
b1000011010010000100010101000011010010110101111101000011010011110101010101001110010101000100010101010010 H
b100 I
b101011011001110000 6
b1 F
1$
#1440
0$
#1460
b10100110101010101000010010101000101001001000001010000110101010000110011 H
1)
b10 F
1$
#1480
0$
#1500
1/
0)
1-
b10100110100100001001001010001100101010001011111010001000100010101000011 H
b11 F
1$
#1520
0$
#1540
b11011101110111011110 *
b11011101110111011110 2
b1110 K
b1 J
b1 7
b101101100111000 "
b101101100111000 0
b101101100111000 4
b1 +
b1 5
b1000011010010000100010101000011010010110101111101000011010011110101010101001110010101000100010101010010 H
0/
0-
b10101101100111000 6
b11 I
b1 F
1$
#1560
0$
#1580
1)
b10100110101010101000010010101000101001001000001010000110101010000110011 H
b10 F
1$
#1600
0$
#1620
b10100110100100001001001010001100101010001011111010001000100010101000011 H
1/
0)
1-
b11 F
1$
#1640
0$
#1660
b11011101110111011101 *
b11011101110111011101 2
b1101 K
b0 J
b0 7
b1010110110011100 "
b1010110110011100 0
b1010110110011100 4
b0 +
b0 5
0/
0-
b1000011010010000100010101000011010010110101111101000011010011110101010101001110010101000100010101010010 H
b10 I
b1010110110011100 6
b1 F
1$
#1680
0$
#1700
b10100110101010101000010010101000101001001000001010000110101010000110011 H
1)
b10 F
1$
#1720
0$
#1740
1/
0)
1-
b10100110100100001001001010001100101010001011111010001000100010101000011 H
b11 F
1$
#1760
0$
#1780
b101011011001110 "
b101011011001110 0
b101011011001110 4
b1000011010010000100010101000011010010110101111101000011010011110101010101001110010101000100010101010010 H
0/
0-
b101011011001110 6
b1 I
b1 F
1$
#1800
0$
#1820
1)
b10100110101010101000010010101000101001001000001010000110101010000110011 H
b10 F
1$
#1840
0$
#1860
b10100110100100001001001010001100101010001011111010001000100010101000011 H
1/
0)
1-
b11 F
1$
#1880
0$
#1900
b10101101100111 "
b10101101100111 0
b10101101100111 4
0/
0-
b1000011010010000100010101000011010010110101111101000011010011110101010101001110010101000100010101010010 H
1,
b0 I
b10101101100111 6
b1 F
1$
#1920
0$
#1940
b10001100100100101001110010010010101001101001000 H
1!
b100 F
1$
#1960
0$
#1980
0!
1.
b101001101010100010000010101001001010100 H
b0 F
1%
1$
0&
b0 #
b0 '
b0 1
#2000
0$
#2020
b0 "
b0 0
b0 4
b10100110100100001001001010001100101010001011111010001000100010101000011 H
1/
0.
1-
b0 6
0,
b10000 I
b11 F
0%
1$
#2040
0$
#2060
0/
0-
b1000011010010000100010101000011010010110101111101000011010011110101010101001110010101000100010101010010 H
b1111 I
b1 F
1$
#2080
0$
#2100
b10100110101010101000010010101000101001001000001010000110101010000110011 H
1)
b10 F
1$
#2120
0$
#2140
1/
0)
1-
b10100110100100001001001010001100101010001011111010001000100010101000011 H
b11 F
1$
#2160
0$
#2180
b1000011010010000100010101000011010010110101111101000011010011110101010101001110010101000100010101010010 H
0/
0-
b1110 I
b1 F
1$
#2200
0$
#2220
1)
b10100110101010101000010010101000101001001000001010000110101010000110011 H
b10 F
1$
#2240
0$
#2260
b10100110100100001001001010001100101010001011111010001000100010101000011 H
1/
0)
1-
b11 F
1$
#2280
0$
#2300
0/
0-
b1000011010010000100010101000011010010110101111101000011010011110101010101001110010101000100010101010010 H
b1101 I
b1 F
1$
#2320
0$
#2340
b10100110101010101000010010101000101001001000001010000110101010000110011 H
1)
b10 F
1$
#2360
0$
#2380
1/
0)
1-
b10100110100100001001001010001100101010001011111010001000100010101000011 H
b11 F
1$
#2400
0$
#2420
b1000011010010000100010101000011010010110101111101000011010011110101010101001110010101000100010101010010 H
0/
0-
b1100 I
b1 F
1$
#2440
0$
#2460
1)
b10100110101010101000010010101000101001001000001010000110101010000110011 H
b10 F
1$
#2480
0$
#2500
b10100110100100001001001010001100101010001011111010001000100010101000011 H
1/
0)
1-
b11 F
1$
#2520
0$
#2540
0/
0-
b1000011010010000100010101000011010010110101111101000011010011110101010101001110010101000100010101010010 H
b1011 I
b1 F
1$
#2560
0$
#2580
b10100110101010101000010010101000101001001000001010000110101010000110011 H
1)
b10 F
1$
#2600
0$
#2620
1/
0)
1-
b10100110100100001001001010001100101010001011111010001000100010101000011 H
b11 F
1$
#2640
0$
#2660
b1000011010010000100010101000011010010110101111101000011010011110101010101001110010101000100010101010010 H
0/
0-
b1010 I
b1 F
1$
#2680
0$
#2700
1)
b10100110101010101000010010101000101001001000001010000110101010000110011 H
b10 F
1$
#2720
0$
#2740
b10100110100100001001001010001100101010001011111010001000100010101000011 H
1/
0)
1-
b11 F
1$
#2760
0$
#2780
0/
0-
b1000011010010000100010101000011010010110101111101000011010011110101010101001110010101000100010101010010 H
b1001 I
b1 F
1$
#2800
0$
#2820
b10100110101010101000010010101000101001001000001010000110101010000110011 H
1)
b10 F
1$
#2840
0$
#2860
1/
0)
1-
b10100110100100001001001010001100101010001011111010001000100010101000011 H
b11 F
1$
#2880
0$
#2900
b1000011010010000100010101000011010010110101111101000011010011110101010101001110010101000100010101010010 H
0/
0-
b1000 I
b1 F
1$
#2920
0$
#2940
1)
b10100110101010101000010010101000101001001000001010000110101010000110011 H
b10 F
1$
#2960
0$
#2980
b10100110100100001001001010001100101010001011111010001000100010101000011 H
1/
0)
1-
b11 F
1$
#3000
0$
#3020
0/
0-
b1000011010010000100010101000011010010110101111101000011010011110101010101001110010101000100010101010010 H
b111 I
b1 F
1$
#3040
0$
#3060
b10100110101010101000010010101000101001001000001010000110101010000110011 H
1)
b10 F
1$
#3080
0$
#3100
1/
0)
1-
b10100110100100001001001010001100101010001011111010001000100010101000011 H
b11 F
1$
#3120
0$
#3140
b1000011010010000100010101000011010010110101111101000011010011110101010101001110010101000100010101010010 H
0/
0-
b110 I
b1 F
1$
#3160
0$
#3180
1)
b10100110101010101000010010101000101001001000001010000110101010000110011 H
b10 F
1$
#3200
0$
#3220
b10100110100100001001001010001100101010001011111010001000100010101000011 H
1/
0)
1-
b11 F
1$
#3240
0$
#3260
0/
0-
b1000011010010000100010101000011010010110101111101000011010011110101010101001110010101000100010101010010 H
b101 I
b1 F
1$
#3280
0$
#3300
b10100110101010101000010010101000101001001000001010000110101010000110011 H
1)
b10 F
1$
#3320
0$
#3340
1/
0)
1-
b10100110100100001001001010001100101010001011111010001000100010101000011 H
b11 F
1$
#3360
0$
#3380
b1000011010010000100010101000011010010110101111101000011010011110101010101001110010101000100010101010010 H
0/
0-
b100 I
b1 F
1$
#3400
0$
#3420
1)
b10100110101010101000010010101000101001001000001010000110101010000110011 H
b10 F
1$
#3440
0$
#3460
b10100110100100001001001010001100101010001011111010001000100010101000011 H
1/
0)
1-
b11 F
1$
#3480
0$
#3500
0/
0-
b1000011010010000100010101000011010010110101111101000011010011110101010101001110010101000100010101010010 H
b11 I
b1 F
1$
#3520
0$
#3540
b10100110101010101000010010101000101001001000001010000110101010000110011 H
1)
b10 F
1$
#3560
0$
#3580
1/
0)
1-
b10100110100100001001001010001100101010001011111010001000100010101000011 H
b11 F
1$
#3600
0$
#3620
b1000011010010000100010101000011010010110101111101000011010011110101010101001110010101000100010101010010 H
0/
0-
b10 I
b1 F
1$
#3640
0$
#3660
1)
b10100110101010101000010010101000101001001000001010000110101010000110011 H
b10 F
1$
#3680
0$
#3700
b10100110100100001001001010001100101010001011111010001000100010101000011 H
1/
0)
1-
b11 F
1$
#3720
0$
#3740
0/
0-
b1000011010010000100010101000011010010110101111101000011010011110101010101001110010101000100010101010010 H
b1 I
b1 F
1$
#3760
0$
#3780
b10100110101010101000010010101000101001001000001010000110101010000110011 H
1)
b10 F
1$
#3800
0$
#3820
1/
0)
1-
b10100110100100001001001010001100101010001011111010001000100010101000011 H
b11 F
1$
#3840
0$
#3860
b1000011010010000100010101000011010010110101111101000011010011110101010101001110010101000100010101010010 H
0/
0-
1,
b0 I
b1 F
1$
#3880
0$
#3900
1!
b10001100100100101001110010010010101001101001000 H
b100 F
1$
#3920
0$
#3940
b101001101010100010000010101001001010100 H
0!
1.
b0 F
1%
1$
b10011001 #
b10011001 '
b10011001 1
0&
#3960
0$
#3980
b110 M
b1001 L
b11011101110101100110 *
b11011101110101100110 2
b110 K
b1001 J
1:
b1001 9
b11 (
b11 3
18
b1001 7
b10011001 +
b10011001 5
1/
0.
1-
b10100110100100001001001010001100101010001011111010001000100010101000011 H
0,
b10000 I
b100110010000000000000000 6
b11 F
0%
1$
#4000
0$
#4020
b1 M
b100 L
b11011101110100011001 *
b11011101110100011001 2
b1001 K
b1100 J
b1 (
b1 3
0:
b100 9
b1100 7
b1000000000000000 "
b1000000000000000 0
b1000000000000000 4
b1001100 +
b1001100 5
b1000011010010000100010101000011010010110101111101000011010011110101010101001110010101000100010101010010 H
0/
0-
b10011001000000000000000 6
b1111 I
b1 F
1$
#4040
0$
#4060
1)
b10100110101010101000010010101000101001001000001010000110101010000110011 H
b10 F
1$
#4080
0$
#4100
b11011101110100010110 *
b11011101110100010110 2
b110 K
b1001 J
b1001 7
b1001001 +
b1001001 5
b10100110100100001001001010001100101010001011111010001000100010101000011 H
1/
0)
1-
b10010011000000000000000 6
b11 F
1$
#4120
0$
#4140
b1111 M
b10 L
b11011101110111110001 *
b11011101110111110001 2
b1 K
b100 J
b10 9
b0 (
b0 3
08
b100 7
b1100000000000000 "
b1100000000000000 0
b1100000000000000 4
b100100 +
b100100 5
0/
0-
b1000011010010000100010101000011010010110101111101000011010011110101010101001110010101000100010101010010 H
b1110 I
b1001001100000000000000 6
b1 F
1$
#4160
0$
#4180
b10100110101010101000010010101000101001001000001010000110101010000110011 H
1)
b10 F
1$
#4200
0$
#4220
1/
0)
1-
b10100110100100001001001010001100101010001011111010001000100010101000011 H
b11 F
1$
#4240
0$
#4260
b1110 M
b1 L
b11011101110111101111 *
b11011101110111101111 2
b1111 K
b10 J
b1 9
b10 7
b110000000000000 "
b110000000000000 0
b110000000000000 4
b10010 +
b10010 5
b1000011010010000100010101000011010010110101111101000011010011110101010101001110010101000100010101010010 H
0/
0-
b100100110000000000000 6
b1101 I
b1 F
1$
#4280
0$
#4300
1)
b10100110101010101000010010101000101001001000001010000110101010000110011 H
b10 F
1$
#4320
0$
#4340
b10100110100100001001001010001100101010001011111010001000100010101000011 H
1/
0)
1-
b11 F
1$
#4360
0$
